{"date":"2025-12-31","importKwh":8.898,"exportKwh":18.713,"importCost":174.2,"exportRevenue":69.89,"netCost":104.31,"avgImportPrice":19.58,"avgExportPrice":3.73,"peakImportPrice":38.63,"spikeCount":0,"highCount":0,"renewablesAvg":36.8,"intervals":[{"nemTime":"2025-12-31T00:05:00+10:00","hour":0,"minute":5,"importKwh":0.051,"exportKwh":0,"importPrice":18.83451,"exportPrice":9.15488,"importCost":0.9606,"exportRevenue":0,"descriptor":"veryLow","spikeStatus":"none","period":"shoulder","renewables":19.36253705521432},{"nemTime":"2025-12-31T00:10:00+10:00","hour":0,"minute":10,"importKwh":0.053,"exportKwh":0,"importPrice":19.85098,"exportPrice":10.07895,"importCost":1.0521,"exportRevenue":0,"descriptor":"veryLow","spikeStatus":"none","period":"shoulder","renewables":19.152763689825903},{"nemTime":"2025-12-31T00:15:00+10:00","hour":0,"minute":15,"importKwh":0.049,"exportKwh":0,"importPrice":19.75265,"exportPrice":9.98956,"importCost":0.9679,"exportRevenue":0,"descriptor":"veryLow","spikeStatus":"none","period":"shoulder","renewables":19.60316817322047},{"nemTime":"2025-12-31T00:20:00+10:00","hour":0,"minute":20,"importKwh":0.048,"exportKwh":0,"importPrice":19.75265,"exportPrice":9.98956,"importCost":0.9481,"exportRevenue":0,"descriptor":"veryLow","spikeStatus":"none","period":"shoulder","renewables":19.37245525970118},{"nemTime":"2025-12-31T00:25:00+10:00","hour":0,"minute":25,"importKwh":0.048,"exportKwh":0,"importPrice":17.62396,"exportPrice":8.05438,"importCost":0.8459,"exportRevenue":0,"descriptor":"veryLow","spikeStatus":"none","period":"shoulder","renewables":19.962405068115647},{"nemTime":"2025-12-31T00:30:00+10:00","hour":0,"minute":30,"importKwh":0.05,"exportKwh":0,"importPrice":16.22981,"exportPrice":6.78697,"importCost":0.8115,"exportRevenue":0,"descriptor":"veryLow","spikeStatus":"none","period":"shoulder","renewables":20.07158981297894},{"nemTime":"2025-12-31T00:35:00+10:00","hour":0,"minute":35,"importKwh":0.048,"exportKwh":0,"importPrice":16.47206,"exportPrice":7.0072,"importCost":0.7907,"exportRevenue":0,"descriptor":"veryLow","spikeStatus":"none","period":"shoulder","renewables":20.246055295684098},{"nemTime":"2025-12-31T00:40:00+10:00","hour":0,"minute":40,"importKwh":0.047,"exportKwh":0,"importPrice":16.45344,"exportPrice":6.99027,"importCost":0.7733,"exportRevenue":0,"descriptor":"veryLow","spikeStatus":"none","period":"shoulder","renewables":20.47706448348262},{"nemTime":"2025-12-31T00:45:00+10:00","hour":0,"minute":45,"importKwh":0.051,"exportKwh":0,"importPrice":16.3992,"exportPrice":6.94097,"importCost":0.8364,"exportRevenue":0,"descriptor":"veryLow","spikeStatus":"none","period":"shoulder","renewables":20.492718418713732},{"nemTime":"2025-12-31T00:50:00+10:00","hour":0,"minute":50,"importKwh":0.052,"exportKwh":0,"importPrice":16.22979,"exportPrice":6.78695,"importCost":0.8439,"exportRevenue":0,"descriptor":"veryLow","spikeStatus":"none","period":"shoulder","renewables":21.315412779890515},{"nemTime":"2025-12-31T00:55:00+10:00","hour":0,"minute":55,"importKwh":0.05,"exportKwh":0,"importPrice":16.22981,"exportPrice":6.78697,"importCost":0.8115,"exportRevenue":0,"descriptor":"veryLow","spikeStatus":"none","period":"shoulder","renewables":21.117139373716633},{"nemTime":"2025-12-31T01:00:00+10:00","hour":1,"minute":0,"importKwh":0.047,"exportKwh":0,"importPrice":16.21808,"exportPrice":6.77631,"importCost":0.7622,"exportRevenue":0,"descriptor":"veryLow","spikeStatus":"none","period":"shoulder","renewables":21.33144039992417},{"nemTime":"2025-12-31T01:05:00+10:00","hour":1,"minute":5,"importKwh":0.042,"exportKwh":0,"importPrice":17.7067,"exportPrice":8.1296,"importCost":0.7437,"exportRevenue":0,"descriptor":"veryLow","spikeStatus":"none","period":"shoulder","renewables":20.881945986320083},{"nemTime":"2025-12-31T01:10:00+10:00","hour":1,"minute":10,"importKwh":0.044,"exportKwh":0,"importPrice":17.69247,"exportPrice":8.11667,"importCost":0.7785,"exportRevenue":0,"descriptor":"veryLow","spikeStatus":"none","period":"shoulder","renewables":20.920616137986535},{"nemTime":"2025-12-31T01:15:00+10:00","hour":1,"minute":15,"importKwh":0.046,"exportKwh":0,"importPrice":17.62396,"exportPrice":8.05438,"importCost":0.8107,"exportRevenue":0,"descriptor":"veryLow","spikeStatus":"none","period":"shoulder","renewables":20.756379173562763},{"nemTime":"2025-12-31T01:20:00+10:00","hour":1,"minute":20,"importKwh":0.047,"exportKwh":0,"importPrice":17.40017,"exportPrice":7.85093,"importCost":0.8178,"exportRevenue":0,"descriptor":"veryLow","spikeStatus":"none","period":"shoulder","renewables":20.794364755149132},{"nemTime":"2025-12-31T01:25:00+10:00","hour":1,"minute":25,"importKwh":0.049,"exportKwh":0,"importPrice":16.78068,"exportPrice":7.28776,"importCost":0.8223,"exportRevenue":0,"descriptor":"veryLow","spikeStatus":"none","period":"shoulder","renewables":20.816088199753537},{"nemTime":"2025-12-31T01:30:00+10:00","hour":1,"minute":30,"importKwh":0.055,"exportKwh":0,"importPrice":16.22981,"exportPrice":6.78697,"importCost":0.8926,"exportRevenue":0,"descriptor":"veryLow","spikeStatus":"none","period":"shoulder","renewables":20.733810270482163},{"nemTime":"2025-12-31T01:35:00+10:00","hour":1,"minute":35,"importKwh":0.054,"exportKwh":0,"importPrice":16.22981,"exportPrice":6.78697,"importCost":0.8764,"exportRevenue":0,"descriptor":"veryLow","spikeStatus":"none","period":"shoulder","renewables":20.610578151627625},{"nemTime":"2025-12-31T01:40:00+10:00","hour":1,"minute":40,"importKwh":0.047,"exportKwh":0,"importPrice":16.22981,"exportPrice":6.78697,"importCost":0.7628,"exportRevenue":0,"descriptor":"veryLow","spikeStatus":"none","period":"shoulder","renewables":20.445351801288155},{"nemTime":"2025-12-31T01:45:00+10:00","hour":1,"minute":45,"importKwh":0.045,"exportKwh":0,"importPrice":16.51726,"exportPrice":7.04829,"importCost":0.7433,"exportRevenue":0,"descriptor":"veryLow","spikeStatus":"none","period":"shoulder","renewables":20.11797213218648},{"nemTime":"2025-12-31T01:50:00+10:00","hour":1,"minute":50,"importKwh":0.045,"exportKwh":0,"importPrice":16.22981,"exportPrice":6.78697,"importCost":0.7303,"exportRevenue":0,"descriptor":"veryLow","spikeStatus":"none","period":"shoulder","renewables":19.738350064894114},{"nemTime":"2025-12-31T01:55:00+10:00","hour":1,"minute":55,"importKwh":0.057,"exportKwh":0,"importPrice":17.38121,"exportPrice":7.8337,"importCost":0.9907,"exportRevenue":0,"descriptor":"veryLow","spikeStatus":"none","period":"shoulder","renewables":19.368326487632412},{"nemTime":"2025-12-31T02:00:00+10:00","hour":2,"minute":0,"importKwh":0.253,"exportKwh":0,"importPrice":16.22981,"exportPrice":6.78697,"importCost":4.1061,"exportRevenue":0,"descriptor":"veryLow","spikeStatus":"none","period":"shoulder","renewables":19.253163498890125},{"nemTime":"2025-12-31T02:05:00+10:00","hour":2,"minute":5,"importKwh":0.213,"exportKwh":0,"importPrice":16.55519,"exportPrice":7.08277,"importCost":3.5263,"exportRevenue":0,"descriptor":"veryLow","spikeStatus":"none","period":"shoulder","renewables":18.850181164160723},{"nemTime":"2025-12-31T02:10:00+10:00","hour":2,"minute":10,"importKwh":0.05,"exportKwh":0,"importPrice":16.22981,"exportPrice":6.78697,"importCost":0.8115,"exportRevenue":0,"descriptor":"veryLow","spikeStatus":"none","period":"shoulder","renewables":18.961945430892023},{"nemTime":"2025-12-31T02:15:00+10:00","hour":2,"minute":15,"importKwh":0.053,"exportKwh":0,"importPrice":16.49994,"exportPrice":7.03254,"importCost":0.8745,"exportRevenue":0,"descriptor":"veryLow","spikeStatus":"none","period":"shoulder","renewables":18.81856397759973},{"nemTime":"2025-12-31T02:20:00+10:00","hour":2,"minute":20,"importKwh":0.05,"exportKwh":0,"importPrice":16.60535,"exportPrice":7.12837,"importCost":0.8303,"exportRevenue":0,"descriptor":"veryLow","spikeStatus":"none","period":"shoulder","renewables":18.165753171680144},{"nemTime":"2025-12-31T02:25:00+10:00","hour":2,"minute":25,"importKwh":0.042,"exportKwh":0,"importPrice":15.19233,"exportPrice":5.84381,"importCost":0.6381,"exportRevenue":0,"descriptor":"veryLow","spikeStatus":"none","period":"shoulder","renewables":17.76420590568594},{"nemTime":"2025-12-31T02:30:00+10:00","hour":2,"minute":30,"importKwh":0.042,"exportKwh":0,"importPrice":16.19586,"exportPrice":6.75611,"importCost":0.6802,"exportRevenue":0,"descriptor":"veryLow","spikeStatus":"none","period":"shoulder","renewables":17.579413534232554},{"nemTime":"2025-12-31T02:35:00+10:00","hour":2,"minute":35,"importKwh":0.046,"exportKwh":0,"importPrice":16.22981,"exportPrice":6.78697,"importCost":0.7466,"exportRevenue":0,"descriptor":"veryLow","spikeStatus":"none","period":"shoulder","renewables":17.32052217677409},{"nemTime":"2025-12-31T02:40:00+10:00","hour":2,"minute":40,"importKwh":0.047,"exportKwh":0,"importPrice":15.14204,"exportPrice":5.79809,"importCost":0.7117,"exportRevenue":0,"descriptor":"veryLow","spikeStatus":"none","period":"shoulder","renewables":17.809390797825},{"nemTime":"2025-12-31T02:45:00+10:00","hour":2,"minute":45,"importKwh":0.046,"exportKwh":0,"importPrice":15.16894,"exportPrice":5.82255,"importCost":0.6978,"exportRevenue":0,"descriptor":"veryLow","spikeStatus":"none","period":"shoulder","renewables":17.739687779747438},{"nemTime":"2025-12-31T02:50:00+10:00","hour":2,"minute":50,"importKwh":0.046,"exportKwh":0,"importPrice":15.92906,"exportPrice":6.51356,"importCost":0.7327,"exportRevenue":0,"descriptor":"veryLow","spikeStatus":"none","period":"shoulder","renewables":17.51383011719094},{"nemTime":"2025-12-31T02:55:00+10:00","hour":2,"minute":55,"importKwh":0.048,"exportKwh":0,"importPrice":15.93142,"exportPrice":6.51571,"importCost":0.7647,"exportRevenue":0,"descriptor":"veryLow","spikeStatus":"none","period":"shoulder","renewables":17.341713017767},{"nemTime":"2025-12-31T03:00:00+10:00","hour":3,"minute":0,"importKwh":0.049,"exportKwh":0,"importPrice":15.19233,"exportPrice":5.84381,"importCost":0.7444,"exportRevenue":0,"descriptor":"veryLow","spikeStatus":"none","period":"shoulder","renewables":17.483146277296825},{"nemTime":"2025-12-31T03:05:00+10:00","hour":3,"minute":5,"importKwh":0.048,"exportKwh":0,"importPrice":15.14009,"exportPrice":5.79632,"importCost":0.7267,"exportRevenue":0,"descriptor":"veryLow","spikeStatus":"none","period":"shoulder","renewables":17.781905971508547},{"nemTime":"2025-12-31T03:10:00+10:00","hour":3,"minute":10,"importKwh":0.047,"exportKwh":0,"importPrice":15.16894,"exportPrice":5.82255,"importCost":0.7129,"exportRevenue":0,"descriptor":"veryLow","spikeStatus":"none","period":"shoulder","renewables":18.278703009189314},{"nemTime":"2025-12-31T03:15:00+10:00","hour":3,"minute":15,"importKwh":0.048,"exportKwh":0,"importPrice":15.16894,"exportPrice":5.82255,"importCost":0.7281,"exportRevenue":0,"descriptor":"veryLow","spikeStatus":"none","period":"shoulder","renewables":18.36723094432744},{"nemTime":"2025-12-31T03:20:00+10:00","hour":3,"minute":20,"importKwh":0.047,"exportKwh":0,"importPrice":15.19233,"exportPrice":5.84381,"importCost":0.714,"exportRevenue":0,"descriptor":"veryLow","spikeStatus":"none","period":"shoulder","renewables":17.86227482920502},{"nemTime":"2025-12-31T03:25:00+10:00","hour":3,"minute":25,"importKwh":0.045,"exportKwh":0,"importPrice":15.16894,"exportPrice":5.82255,"importCost":0.6826,"exportRevenue":0,"descriptor":"veryLow","spikeStatus":"none","period":"shoulder","renewables":17.422302073850705},{"nemTime":"2025-12-31T03:30:00+10:00","hour":3,"minute":30,"importKwh":0.045,"exportKwh":0,"importPrice":15.92425,"exportPrice":6.50919,"importCost":0.7166,"exportRevenue":0,"descriptor":"veryLow","spikeStatus":"none","period":"shoulder","renewables":16.59194324767845},{"nemTime":"2025-12-31T03:35:00+10:00","hour":3,"minute":35,"importKwh":0.043,"exportKwh":0,"importPrice":16.21808,"exportPrice":6.77631,"importCost":0.6974,"exportRevenue":0,"descriptor":"veryLow","spikeStatus":"none","period":"shoulder","renewables":15.561597753587876},{"nemTime":"2025-12-31T03:40:00+10:00","hour":3,"minute":40,"importKwh":0.047,"exportKwh":0,"importPrice":15.17454,"exportPrice":5.82764,"importCost":0.7132,"exportRevenue":0,"descriptor":"veryLow","spikeStatus":"none","period":"shoulder","renewables":15.288356264117173},{"nemTime":"2025-12-31T03:45:00+10:00","hour":3,"minute":45,"importKwh":0.044,"exportKwh":0,"importPrice":15.19233,"exportPrice":5.84381,"importCost":0.6685,"exportRevenue":0,"descriptor":"veryLow","spikeStatus":"none","period":"shoulder","renewables":14.62985395014166},{"nemTime":"2025-12-31T03:50:00+10:00","hour":3,"minute":50,"importKwh":0.046,"exportKwh":0,"importPrice":15.19233,"exportPrice":5.84381,"importCost":0.6988,"exportRevenue":0,"descriptor":"veryLow","spikeStatus":"none","period":"shoulder","renewables":14.22260486633157},{"nemTime":"2025-12-31T03:55:00+10:00","hour":3,"minute":55,"importKwh":0.047,"exportKwh":0,"importPrice":15.19233,"exportPrice":5.84381,"importCost":0.714,"exportRevenue":0,"descriptor":"veryLow","spikeStatus":"none","period":"shoulder","renewables":14.035154494356952},{"nemTime":"2025-12-31T04:00:00+10:00","hour":4,"minute":0,"importKwh":0.048,"exportKwh":0,"importPrice":16.19586,"exportPrice":6.75611,"importCost":0.7774,"exportRevenue":0,"descriptor":"veryLow","spikeStatus":"none","period":"shoulder","renewables":13.78036511257134},{"nemTime":"2025-12-31T04:05:00+10:00","hour":4,"minute":5,"importKwh":0.047,"exportKwh":0,"importPrice":16.2298,"exportPrice":6.78696,"importCost":0.7628,"exportRevenue":0,"descriptor":"veryLow","spikeStatus":"none","period":"shoulder","renewables":14.16566025973658},{"nemTime":"2025-12-31T04:10:00+10:00","hour":4,"minute":10,"importKwh":0.046,"exportKwh":0,"importPrice":15.19233,"exportPrice":5.84381,"importCost":0.6988,"exportRevenue":0,"descriptor":"veryLow","spikeStatus":"none","period":"shoulder","renewables":14.095008945981647},{"nemTime":"2025-12-31T04:15:00+10:00","hour":4,"minute":15,"importKwh":0.045,"exportKwh":0,"importPrice":15.30352,"exportPrice":5.94489,"importCost":0.6887,"exportRevenue":0,"descriptor":"veryLow","spikeStatus":"none","period":"shoulder","renewables":14.13545689659695},{"nemTime":"2025-12-31T04:20:00+10:00","hour":4,"minute":20,"importKwh":0.044,"exportKwh":0,"importPrice":15.39319,"exportPrice":6.02641,"importCost":0.6773,"exportRevenue":0,"descriptor":"veryLow","spikeStatus":"none","period":"shoulder","renewables":13.898822277011627},{"nemTime":"2025-12-31T04:25:00+10:00","hour":4,"minute":25,"importKwh":0.051,"exportKwh":0,"importPrice":15.21365,"exportPrice":5.86319,"importCost":0.7759,"exportRevenue":0,"descriptor":"veryLow","spikeStatus":"none","period":"shoulder","renewables":14.66660424920246},{"nemTime":"2025-12-31T04:30:00+10:00","hour":4,"minute":30,"importKwh":0.05,"exportKwh":0,"importPrice":15.25672,"exportPrice":5.90235,"importCost":0.7628,"exportRevenue":0,"descriptor":"veryLow","spikeStatus":"none","period":"shoulder","renewables":14.887179917928794},{"nemTime":"2025-12-31T04:35:00+10:00","hour":4,"minute":35,"importKwh":0.045,"exportKwh":0,"importPrice":15.25788,"exportPrice":5.9034,"importCost":0.6866,"exportRevenue":0,"descriptor":"veryLow","spikeStatus":"none","period":"shoulder","renewables":14.91623646777788},{"nemTime":"2025-12-31T04:40:00+10:00","hour":4,"minute":40,"importKwh":0.046,"exportKwh":0,"importPrice":15.26496,"exportPrice":5.90984,"importCost":0.7022,"exportRevenue":0,"descriptor":"veryLow","spikeStatus":"none","period":"shoulder","renewables":14.830427719470373},{"nemTime":"2025-12-31T04:45:00+10:00","hour":4,"minute":45,"importKwh":0.043,"exportKwh":0,"importPrice":15.19233,"exportPrice":5.84381,"importCost":0.6533,"exportRevenue":0,"descriptor":"veryLow","spikeStatus":"none","period":"shoulder","renewables":14.810058551178509},{"nemTime":"2025-12-31T04:50:00+10:00","hour":4,"minute":50,"importKwh":0.044,"exportKwh":0,"importPrice":15.25615,"exportPrice":5.90183,"importCost":0.6713,"exportRevenue":0,"descriptor":"veryLow","spikeStatus":"none","period":"shoulder","renewables":14.791921375091945},{"nemTime":"2025-12-31T04:55:00+10:00","hour":4,"minute":55,"importKwh":0.043,"exportKwh":0,"importPrice":15.38194,"exportPrice":6.01618,"importCost":0.6614,"exportRevenue":0,"descriptor":"veryLow","spikeStatus":"none","period":"shoulder","renewables":15.001360981672477},{"nemTime":"2025-12-31T05:00:00+10:00","hour":5,"minute":0,"importKwh":0.043,"exportKwh":0,"importPrice":15.42825,"exportPrice":6.05828,"importCost":0.6634,"exportRevenue":0,"descriptor":"veryLow","spikeStatus":"none","period":"shoulder","renewables":14.685914288657125},{"nemTime":"2025-12-31T05:05:00+10:00","hour":5,"minute":5,"importKwh":0.048,"exportKwh":0,"importPrice":16.1982,"exportPrice":6.75824,"importCost":0.7775,"exportRevenue":0,"descriptor":"veryLow","spikeStatus":"none","period":"shoulder","renewables":15.497322015255028},{"nemTime":"2025-12-31T05:10:00+10:00","hour":5,"minute":10,"importKwh":0.05,"exportKwh":0,"importPrice":15.4242,"exportPrice":6.0546,"importCost":0.7712,"exportRevenue":0,"descriptor":"veryLow","spikeStatus":"none","period":"shoulder","renewables":15.707637970915094},{"nemTime":"2025-12-31T05:15:00+10:00","hour":5,"minute":15,"importKwh":0.046,"exportKwh":0,"importPrice":16.22981,"exportPrice":6.78697,"importCost":0.7466,"exportRevenue":0,"descriptor":"veryLow","spikeStatus":"none","period":"shoulder","renewables":16.05272091915975},{"nemTime":"2025-12-31T05:20:00+10:00","hour":5,"minute":20,"importKwh":0.036,"exportKwh":0,"importPrice":16.22981,"exportPrice":6.78697,"importCost":0.5843,"exportRevenue":0,"descriptor":"veryLow","spikeStatus":"none","period":"shoulder","renewables":15.894435675331712},{"nemTime":"2025-12-31T05:25:00+10:00","hour":5,"minute":25,"importKwh":0.033,"exportKwh":0,"importPrice":15.53156,"exportPrice":6.1522,"importCost":0.5125,"exportRevenue":0,"descriptor":"veryLow","spikeStatus":"none","period":"shoulder","renewables":17.014504630296614},{"nemTime":"2025-12-31T05:30:00+10:00","hour":5,"minute":30,"importKwh":0.031,"exportKwh":0,"importPrice":15.19233,"exportPrice":5.84381,"importCost":0.471,"exportRevenue":0,"descriptor":"veryLow","spikeStatus":"none","period":"shoulder","renewables":17.691855641021085},{"nemTime":"2025-12-31T05:35:00+10:00","hour":5,"minute":35,"importKwh":0.029,"exportKwh":0,"importPrice":15.16543,"exportPrice":5.81936,"importCost":0.4398,"exportRevenue":0,"descriptor":"veryLow","spikeStatus":"none","period":"shoulder","renewables":22.253713472480342},{"nemTime":"2025-12-31T05:40:00+10:00","hour":5,"minute":40,"importKwh":0.027,"exportKwh":0,"importPrice":14.02038,"exportPrice":4.7784,"importCost":0.3786,"exportRevenue":0,"descriptor":"veryLow","spikeStatus":"none","period":"shoulder","renewables":24.049854162022843},{"nemTime":"2025-12-31T05:45:00+10:00","hour":5,"minute":45,"importKwh":0.026,"exportKwh":0,"importPrice":8.76414,"exportPrice":0,"importCost":0.2279,"exportRevenue":0,"descriptor":"extremelyLow","spikeStatus":"none","period":"shoulder","renewables":25.533599405803304},{"nemTime":"2025-12-31T05:50:00+10:00","hour":5,"minute":50,"importKwh":0.027,"exportKwh":0,"importPrice":8.00974,"exportPrice":0.68582,"importCost":0.2163,"exportRevenue":0,"descriptor":"extremelyLow","spikeStatus":"none","period":"shoulder","renewables":26.068073143544023},{"nemTime":"2025-12-31T05:55:00+10:00","hour":5,"minute":55,"importKwh":0.029,"exportKwh":0,"importPrice":7.79921,"exportPrice":0.87721,"importCost":0.2262,"exportRevenue":0,"descriptor":"extremelyLow","spikeStatus":"none","period":"shoulder","renewables":26.611783540276313},{"nemTime":"2025-12-31T06:00:00+10:00","hour":6,"minute":0,"importKwh":0.024,"exportKwh":0,"importPrice":7.59336,"exportPrice":1.06435,"importCost":0.1822,"exportRevenue":0,"descriptor":"extremelyLow","spikeStatus":"none","period":"shoulder","renewables":26.980617738509878},{"nemTime":"2025-12-31T06:05:00+10:00","hour":6,"minute":5,"importKwh":0.014,"exportKwh":0,"importPrice":7.80506,"exportPrice":0.87189,"importCost":0.1093,"exportRevenue":0,"descriptor":"extremelyLow","spikeStatus":"none","period":"shoulder","renewables":32.62239670194072},{"nemTime":"2025-12-31T06:10:00+10:00","hour":6,"minute":10,"importKwh":0.008,"exportKwh":0,"importPrice":7.80506,"exportPrice":0.87189,"importCost":0.0624,"exportRevenue":0,"descriptor":"extremelyLow","spikeStatus":"none","period":"shoulder","renewables":33.075558821913695},{"nemTime":"2025-12-31T06:15:00+10:00","hour":6,"minute":15,"importKwh":0.005,"exportKwh":0,"importPrice":7.79921,"exportPrice":0.87721,"importCost":0.039,"exportRevenue":0,"descriptor":"extremelyLow","spikeStatus":"none","period":"shoulder","renewables":34.08502964299409},{"nemTime":"2025-12-31T06:20:00+10:00","hour":6,"minute":20,"importKwh":0.002,"exportKwh":0,"importPrice":7.43803,"exportPrice":1.20555,"importCost":0.0149,"exportRevenue":0,"descriptor":"extremelyLow","spikeStatus":"none","period":"shoulder","renewables":34.167305067168584},{"nemTime":"2025-12-31T06:25:00+10:00","hour":6,"minute":25,"importKwh":0.002,"exportKwh":0,"importPrice":7.47582,"exportPrice":1.1712,"importCost":0.015,"exportRevenue":0,"descriptor":"extremelyLow","spikeStatus":"none","period":"shoulder","renewables":33.759739309240324},{"nemTime":"2025-12-31T06:30:00+10:00","hour":6,"minute":30,"importKwh":0.002,"exportKwh":0,"importPrice":7.80506,"exportPrice":0.87189,"importCost":0.0156,"exportRevenue":0,"descriptor":"extremelyLow","spikeStatus":"none","period":"shoulder","renewables":35.56283526630502},{"nemTime":"2025-12-31T06:35:00+10:00","hour":6,"minute":35,"importKwh":0.005,"exportKwh":0,"importPrice":7.80389,"exportPrice":0.87296,"importCost":0.039,"exportRevenue":0,"descriptor":"extremelyLow","spikeStatus":"none","period":"shoulder","renewables":42.734581210081565},{"nemTime":"2025-12-31T06:40:00+10:00","hour":6,"minute":40,"importKwh":0.014,"exportKwh":0,"importPrice":7.9267,"exportPrice":0.76131,"importCost":0.111,"exportRevenue":0,"descriptor":"extremelyLow","spikeStatus":"none","period":"shoulder","renewables":45.13709305200319},{"nemTime":"2025-12-31T06:45:00+10:00","hour":6,"minute":45,"importKwh":0.017,"exportKwh":0,"importPrice":7.91266,"exportPrice":0.77407,"importCost":0.1345,"exportRevenue":0,"descriptor":"extremelyLow","spikeStatus":"none","period":"shoulder","renewables":44.89882754864012},{"nemTime":"2025-12-31T06:50:00+10:00","hour":6,"minute":50,"importKwh":0.019,"exportKwh":0,"importPrice":8.00974,"exportPrice":0.68582,"importCost":0.1522,"exportRevenue":0,"descriptor":"extremelyLow","spikeStatus":"none","period":"shoulder","renewables":48.23901175078249},{"nemTime":"2025-12-31T06:55:00+10:00","hour":6,"minute":55,"importKwh":0.018,"exportKwh":0,"importPrice":8.00272,"exportPrice":0.6922,"importCost":0.144,"exportRevenue":0,"descriptor":"extremelyLow","spikeStatus":"none","period":"shoulder","renewables":48.62094149511594},{"nemTime":"2025-12-31T07:00:00+10:00","hour":7,"minute":0,"importKwh":0.017,"exportKwh":0,"importPrice":8.00272,"exportPrice":0.6922,"importCost":0.136,"exportRevenue":0,"descriptor":"extremelyLow","spikeStatus":"none","period":"shoulder","renewables":48.32290231646641},{"nemTime":"2025-12-31T07:05:00+10:00","hour":7,"minute":5,"importKwh":0.018,"exportKwh":0,"importPrice":8.00389,"exportPrice":0.69113,"importCost":0.1441,"exportRevenue":0,"descriptor":"extremelyLow","spikeStatus":"none","period":"shoulder","renewables":55.19760341015009},{"nemTime":"2025-12-31T07:10:00+10:00","hour":7,"minute":10,"importKwh":0.018,"exportKwh":0,"importPrice":8.03196,"exportPrice":0.66562,"importCost":0.1446,"exportRevenue":0,"descriptor":"extremelyLow","spikeStatus":"none","period":"shoulder","renewables":58.59627015448746},{"nemTime":"2025-12-31T07:15:00+10:00","hour":7,"minute":15,"importKwh":0.018,"exportKwh":0,"importPrice":8.00272,"exportPrice":0.6922,"importCost":0.144,"exportRevenue":0,"descriptor":"extremelyLow","spikeStatus":"none","period":"shoulder","renewables":57.593941401588054},{"nemTime":"2025-12-31T07:20:00+10:00","hour":7,"minute":20,"importKwh":0.017,"exportKwh":0,"importPrice":8.00272,"exportPrice":0.6922,"importCost":0.136,"exportRevenue":0,"descriptor":"extremelyLow","spikeStatus":"none","period":"shoulder","renewables":56.786627745105655},{"nemTime":"2025-12-31T07:25:00+10:00","hour":7,"minute":25,"importKwh":0.005,"exportKwh":0.122,"importPrice":8.76414,"exportPrice":0,"importCost":0.0438,"exportRevenue":0,"descriptor":"extremelyLow","spikeStatus":"none","period":"shoulder","renewables":61.55404263841046},{"nemTime":"2025-12-31T07:30:00+10:00","hour":7,"minute":30,"importKwh":0,"exportKwh":0.227,"importPrice":8.76414,"exportPrice":0,"importCost":0,"exportRevenue":0,"descriptor":"extremelyLow","spikeStatus":"none","period":"shoulder","renewables":63.84460296606087},{"nemTime":"2025-12-31T07:35:00+10:00","hour":7,"minute":35,"importKwh":0.017,"exportKwh":0.044,"importPrice":8.06354,"exportPrice":0.63691,"importCost":0.1371,"exportRevenue":0.028,"descriptor":"extremelyLow","spikeStatus":"none","period":"shoulder","renewables":65.4666097459392},{"nemTime":"2025-12-31T07:40:00+10:00","hour":7,"minute":40,"importKwh":0.017,"exportKwh":0,"importPrice":8.00272,"exportPrice":0.6922,"importCost":0.136,"exportRevenue":0,"descriptor":"extremelyLow","spikeStatus":"none","period":"shoulder","renewables":64.50464569212319},{"nemTime":"2025-12-31T07:45:00+10:00","hour":7,"minute":45,"importKwh":0.002,"exportKwh":0.178,"importPrice":8.76414,"exportPrice":0,"importCost":0.0175,"exportRevenue":0,"descriptor":"extremelyLow","spikeStatus":"none","period":"shoulder","renewables":65.78414204748724},{"nemTime":"2025-12-31T07:50:00+10:00","hour":7,"minute":50,"importKwh":0.013,"exportKwh":0.049,"importPrice":8.00272,"exportPrice":0.6922,"importCost":0.104,"exportRevenue":0.0339,"descriptor":"extremelyLow","spikeStatus":"none","period":"shoulder","renewables":65.62823127174194},{"nemTime":"2025-12-31T07:55:00+10:00","hour":7,"minute":55,"importKwh":0.017,"exportKwh":0,"importPrice":8.00272,"exportPrice":0.6922,"importCost":0.136,"exportRevenue":0,"descriptor":"extremelyLow","spikeStatus":"none","period":"shoulder","renewables":65.09371473806006},{"nemTime":"2025-12-31T08:00:00+10:00","hour":8,"minute":0,"importKwh":0.015,"exportKwh":0,"importPrice":8.03196,"exportPrice":0.66562,"importCost":0.1205,"exportRevenue":0,"descriptor":"extremelyLow","spikeStatus":"none","period":"shoulder","renewables":68.27880691637816},{"nemTime":"2025-12-31T08:05:00+10:00","hour":8,"minute":5,"importKwh":0.017,"exportKwh":0,"importPrice":8.00389,"exportPrice":0.69113,"importCost":0.1361,"exportRevenue":0,"descriptor":"extremelyLow","spikeStatus":"none","period":"shoulder","renewables":70.24505416363307},{"nemTime":"2025-12-31T08:10:00+10:00","hour":8,"minute":10,"importKwh":0.019,"exportKwh":0,"importPrice":8.03196,"exportPrice":0.66562,"importCost":0.1526,"exportRevenue":0,"descriptor":"extremelyLow","spikeStatus":"none","period":"shoulder","renewables":70.87247014978686},{"nemTime":"2025-12-31T08:15:00+10:00","hour":8,"minute":15,"importKwh":0.018,"exportKwh":0,"importPrice":8.00272,"exportPrice":0.6922,"importCost":0.144,"exportRevenue":0,"descriptor":"extremelyLow","spikeStatus":"none","period":"shoulder","renewables":72.10592870056183},{"nemTime":"2025-12-31T08:20:00+10:00","hour":8,"minute":20,"importKwh":0.017,"exportKwh":0,"importPrice":8.20253,"exportPrice":0.51055,"importCost":0.1394,"exportRevenue":0,"descriptor":"extremelyLow","spikeStatus":"none","period":"shoulder","renewables":71.8845708854979},{"nemTime":"2025-12-31T08:25:00+10:00","hour":8,"minute":25,"importKwh":0.017,"exportKwh":0.001,"importPrice":8.00272,"exportPrice":0.6922,"importCost":0.136,"exportRevenue":0.0007,"descriptor":"extremelyLow","spikeStatus":"none","period":"shoulder","renewables":71.97816139333007},{"nemTime":"2025-12-31T08:30:00+10:00","hour":8,"minute":30,"importKwh":0.019,"exportKwh":0,"importPrice":8.00389,"exportPrice":0.69113,"importCost":0.1521,"exportRevenue":0,"descriptor":"extremelyLow","spikeStatus":"none","period":"shoulder","renewables":72.31649435179308},{"nemTime":"2025-12-31T08:35:00+10:00","hour":8,"minute":35,"importKwh":0.02,"exportKwh":0,"importPrice":7.9267,"exportPrice":0.76131,"importCost":0.1585,"exportRevenue":0,"descriptor":"extremelyLow","spikeStatus":"none","period":"shoulder","renewables":72.9587543963727},{"nemTime":"2025-12-31T08:40:00+10:00","hour":8,"minute":40,"importKwh":0.02,"exportKwh":0,"importPrice":7.80506,"exportPrice":0.87189,"importCost":0.1561,"exportRevenue":0,"descriptor":"extremelyLow","spikeStatus":"none","period":"shoulder","renewables":71.55981995292976},{"nemTime":"2025-12-31T08:45:00+10:00","hour":8,"minute":45,"importKwh":0.018,"exportKwh":0,"importPrice":8.00272,"exportPrice":0.6922,"importCost":0.144,"exportRevenue":0,"descriptor":"extremelyLow","spikeStatus":"none","period":"shoulder","renewables":74.08196478295744},{"nemTime":"2025-12-31T08:50:00+10:00","hour":8,"minute":50,"importKwh":0.02,"exportKwh":0,"importPrice":7.80506,"exportPrice":0.87189,"importCost":0.1561,"exportRevenue":0,"descriptor":"extremelyLow","spikeStatus":"none","period":"shoulder","renewables":70.80618585977862},{"nemTime":"2025-12-31T08:55:00+10:00","hour":8,"minute":55,"importKwh":0.019,"exportKwh":0,"importPrice":8.03196,"exportPrice":0.66562,"importCost":0.1526,"exportRevenue":0,"descriptor":"extremelyLow","spikeStatus":"none","period":"shoulder","renewables":75.45367391406425},{"nemTime":"2025-12-31T09:00:00+10:00","hour":9,"minute":0,"importKwh":0.02,"exportKwh":0,"importPrice":7.80389,"exportPrice":0.87296,"importCost":0.1561,"exportRevenue":0,"descriptor":"extremelyLow","spikeStatus":"none","period":"shoulder","renewables":71.80724465208341},{"nemTime":"2025-12-31T09:05:00+10:00","hour":9,"minute":5,"importKwh":0.019,"exportKwh":0,"importPrice":8.00272,"exportPrice":0.6922,"importCost":0.1521,"exportRevenue":0,"descriptor":"extremelyLow","spikeStatus":"none","period":"shoulder","renewables":76.11847958063026},{"nemTime":"2025-12-31T09:10:00+10:00","hour":9,"minute":10,"importKwh":0.013,"exportKwh":0,"importPrice":8.00389,"exportPrice":0.69113,"importCost":0.1041,"exportRevenue":0,"descriptor":"extremelyLow","spikeStatus":"none","period":"shoulder","renewables":76.72635773382866},{"nemTime":"2025-12-31T09:15:00+10:00","hour":9,"minute":15,"importKwh":0.016,"exportKwh":0,"importPrice":8.03196,"exportPrice":0.66562,"importCost":0.1285,"exportRevenue":0,"descriptor":"extremelyLow","spikeStatus":"none","period":"shoulder","renewables":77.84988286949425},{"nemTime":"2025-12-31T09:20:00+10:00","hour":9,"minute":20,"importKwh":0.017,"exportKwh":0,"importPrice":8.00272,"exportPrice":0.6922,"importCost":0.136,"exportRevenue":0,"descriptor":"extremelyLow","spikeStatus":"none","period":"shoulder","renewables":77.75737083440978},{"nemTime":"2025-12-31T09:25:00+10:00","hour":9,"minute":25,"importKwh":0.015,"exportKwh":0,"importPrice":7.91266,"exportPrice":0.77407,"importCost":0.1187,"exportRevenue":0,"descriptor":"extremelyLow","spikeStatus":"none","period":"shoulder","renewables":77.81976835447401},{"nemTime":"2025-12-31T09:30:00+10:00","hour":9,"minute":30,"importKwh":0.018,"exportKwh":0.001,"importPrice":8.00506,"exportPrice":0.69007,"importCost":0.1441,"exportRevenue":0.0007,"descriptor":"extremelyLow","spikeStatus":"none","period":"shoulder","renewables":79.32550428058298},{"nemTime":"2025-12-31T09:35:00+10:00","hour":9,"minute":35,"importKwh":0.019,"exportKwh":0,"importPrice":7.80506,"exportPrice":0.87189,"importCost":0.1483,"exportRevenue":0,"descriptor":"extremelyLow","spikeStatus":"none","period":"shoulder","renewables":76.29617660032646},{"nemTime":"2025-12-31T09:40:00+10:00","hour":9,"minute":40,"importKwh":0.011,"exportKwh":0,"importPrice":8.00506,"exportPrice":0.69007,"importCost":0.0881,"exportRevenue":0,"descriptor":"extremelyLow","spikeStatus":"none","period":"shoulder","renewables":80.81894494837614},{"nemTime":"2025-12-31T09:45:00+10:00","hour":9,"minute":45,"importKwh":0.012,"exportKwh":0,"importPrice":7.88576,"exportPrice":0.79853,"importCost":0.0946,"exportRevenue":0,"descriptor":"extremelyLow","spikeStatus":"none","period":"shoulder","renewables":78.13833772575249},{"nemTime":"2025-12-31T09:50:00+10:00","hour":9,"minute":50,"importKwh":0.013,"exportKwh":0,"importPrice":7.91266,"exportPrice":0.77407,"importCost":0.1029,"exportRevenue":0,"descriptor":"extremelyLow","spikeStatus":"none","period":"shoulder","renewables":79.06226459580344},{"nemTime":"2025-12-31T09:55:00+10:00","hour":9,"minute":55,"importKwh":0.011,"exportKwh":0,"importPrice":7.80506,"exportPrice":0.87189,"importCost":0.0859,"exportRevenue":0,"descriptor":"extremelyLow","spikeStatus":"none","period":"shoulder","renewables":78.00316411974335},{"nemTime":"2025-12-31T10:00:00+10:00","hour":10,"minute":0,"importKwh":0.014,"exportKwh":0,"importPrice":7.80389,"exportPrice":0.87296,"importCost":0.1093,"exportRevenue":0,"descriptor":"extremelyLow","spikeStatus":"none","period":"shoulder","renewables":78.82804348036629},{"nemTime":"2025-12-31T10:05:00+10:00","hour":10,"minute":5,"importKwh":0.011,"exportKwh":0,"importPrice":7.80389,"exportPrice":0.87296,"importCost":0.0858,"exportRevenue":0,"descriptor":"extremelyLow","spikeStatus":"none","period":"shoulder","renewables":80.08005416013907},{"nemTime":"2025-12-31T10:10:00+10:00","hour":10,"minute":10,"importKwh":0.012,"exportKwh":0,"importPrice":7.80389,"exportPrice":0.87296,"importCost":0.0936,"exportRevenue":0,"descriptor":"extremelyLow","spikeStatus":"none","period":"shoulder","renewables":79.65583310814002},{"nemTime":"2025-12-31T10:15:00+10:00","hour":10,"minute":15,"importKwh":0.015,"exportKwh":0,"importPrice":7.80389,"exportPrice":0.87296,"importCost":0.1171,"exportRevenue":0,"descriptor":"extremelyLow","spikeStatus":"none","period":"shoulder","renewables":79.2634342601456},{"nemTime":"2025-12-31T10:20:00+10:00","hour":10,"minute":20,"importKwh":0.013,"exportKwh":0.001,"importPrice":7.79921,"exportPrice":0.87721,"importCost":0.1014,"exportRevenue":0.0009,"descriptor":"extremelyLow","spikeStatus":"none","period":"shoulder","renewables":77.73684044879052},{"nemTime":"2025-12-31T10:25:00+10:00","hour":10,"minute":25,"importKwh":0.013,"exportKwh":0,"importPrice":7.79921,"exportPrice":0.87721,"importCost":0.1014,"exportRevenue":0,"descriptor":"extremelyLow","spikeStatus":"none","period":"shoulder","renewables":78.45067578333615},{"nemTime":"2025-12-31T10:30:00+10:00","hour":10,"minute":30,"importKwh":0.014,"exportKwh":0,"importPrice":7.80506,"exportPrice":0.87189,"importCost":0.1093,"exportRevenue":0,"descriptor":"extremelyLow","spikeStatus":"none","period":"shoulder","renewables":77.71782145569985},{"nemTime":"2025-12-31T10:35:00+10:00","hour":10,"minute":35,"importKwh":0.011,"exportKwh":0,"importPrice":7.80506,"exportPrice":0.87189,"importCost":0.0859,"exportRevenue":0,"descriptor":"extremelyLow","spikeStatus":"none","period":"shoulder","renewables":78.85460224682613},{"nemTime":"2025-12-31T10:40:00+10:00","hour":10,"minute":40,"importKwh":0.002,"exportKwh":0,"importPrice":7.9267,"exportPrice":0.76131,"importCost":0.0159,"exportRevenue":0,"descriptor":"extremelyLow","spikeStatus":"none","period":"shoulder","renewables":81.29303686818174},{"nemTime":"2025-12-31T10:45:00+10:00","hour":10,"minute":45,"importKwh":0.003,"exportKwh":0,"importPrice":7.79921,"exportPrice":0.87721,"importCost":0.0234,"exportRevenue":0,"descriptor":"extremelyLow","spikeStatus":"none","period":"shoulder","renewables":77.23080066041781},{"nemTime":"2025-12-31T10:50:00+10:00","hour":10,"minute":50,"importKwh":0.003,"exportKwh":0,"importPrice":7.79922,"exportPrice":0.8772,"importCost":0.0234,"exportRevenue":0,"descriptor":"extremelyLow","spikeStatus":"none","period":"shoulder","renewables":78.31052516951355},{"nemTime":"2025-12-31T10:55:00+10:00","hour":10,"minute":55,"importKwh":0.004,"exportKwh":0,"importPrice":7.59336,"exportPrice":1.06435,"importCost":0.0304,"exportRevenue":0,"descriptor":"extremelyLow","spikeStatus":"none","period":"shoulder","renewables":75.18180596701998},{"nemTime":"2025-12-31T11:00:00+10:00","hour":11,"minute":0,"importKwh":0.013,"exportKwh":0,"importPrice":7.88576,"exportPrice":0.79853,"importCost":0.1025,"exportRevenue":0,"descriptor":"extremelyLow","spikeStatus":"none","period":"shoulder","renewables":79.21663677867906},{"nemTime":"2025-12-31T11:05:00+10:00","hour":11,"minute":5,"importKwh":0.012,"exportKwh":0,"importPrice":2.51537,"exportPrice":1.2887,"importCost":0.0302,"exportRevenue":0,"descriptor":"extremelyLow","spikeStatus":"none","period":"offPeak","renewables":73.53280341612196},{"nemTime":"2025-12-31T11:10:00+10:00","hour":11,"minute":10,"importKwh":0.012,"exportKwh":0,"importPrice":2.84403,"exportPrice":0.98992,"importCost":0.0341,"exportRevenue":0,"descriptor":"extremelyLow","spikeStatus":"none","period":"offPeak","renewables":73.81385989321379},{"nemTime":"2025-12-31T11:15:00+10:00","hour":11,"minute":15,"importKwh":0.011,"exportKwh":0,"importPrice":2.76216,"exportPrice":1.06435,"importCost":0.0304,"exportRevenue":0,"descriptor":"extremelyLow","spikeStatus":"none","period":"offPeak","renewables":72.20494689865103},{"nemTime":"2025-12-31T11:20:00+10:00","hour":11,"minute":20,"importKwh":0.013,"exportKwh":0,"importPrice":3.04569,"exportPrice":0.80659,"importCost":0.0396,"exportRevenue":0,"descriptor":"extremelyLow","spikeStatus":"none","period":"offPeak","renewables":74.04048746189916},{"nemTime":"2025-12-31T11:25:00+10:00","hour":11,"minute":25,"importKwh":0.013,"exportKwh":0,"importPrice":2.96801,"exportPrice":0.87721,"importCost":0.0386,"exportRevenue":0,"descriptor":"extremelyLow","spikeStatus":"none","period":"offPeak","renewables":74.31960118112461},{"nemTime":"2025-12-31T11:30:00+10:00","hour":11,"minute":30,"importKwh":0.011,"exportKwh":0.001,"importPrice":2.79024,"exportPrice":1.03882,"importCost":0.0307,"exportRevenue":0.001,"descriptor":"extremelyLow","spikeStatus":"none","period":"offPeak","renewables":72.67080039257246},{"nemTime":"2025-12-31T11:35:00+10:00","hour":11,"minute":35,"importKwh":0.013,"exportKwh":0,"importPrice":2.76216,"exportPrice":1.06435,"importCost":0.0359,"exportRevenue":0,"descriptor":"extremelyLow","spikeStatus":"none","period":"offPeak","renewables":73.03654746563681},{"nemTime":"2025-12-31T11:40:00+10:00","hour":11,"minute":40,"importKwh":0.014,"exportKwh":0,"importPrice":2.76216,"exportPrice":1.06435,"importCost":0.0387,"exportRevenue":0,"descriptor":"extremelyLow","spikeStatus":"none","period":"offPeak","renewables":72.13208678807295},{"nemTime":"2025-12-31T11:45:00+10:00","hour":11,"minute":45,"importKwh":0.014,"exportKwh":0,"importPrice":2.96802,"exportPrice":0.8772,"importCost":0.0416,"exportRevenue":0,"descriptor":"extremelyLow","spikeStatus":"none","period":"offPeak","renewables":73.26758058432735},{"nemTime":"2025-12-31T11:50:00+10:00","hour":11,"minute":50,"importKwh":0.016,"exportKwh":0,"importPrice":2.58437,"exportPrice":1.22598,"importCost":0.0413,"exportRevenue":0,"descriptor":"extremelyLow","spikeStatus":"none","period":"offPeak","renewables":71.55919059998021},{"nemTime":"2025-12-31T11:55:00+10:00","hour":11,"minute":55,"importKwh":0.007,"exportKwh":0,"importPrice":2.76216,"exportPrice":1.06435,"importCost":0.0193,"exportRevenue":0,"descriptor":"extremelyLow","spikeStatus":"none","period":"offPeak","renewables":73.59148069325782},{"nemTime":"2025-12-31T12:00:00+10:00","hour":12,"minute":0,"importKwh":0.002,"exportKwh":0,"importPrice":3.05456,"exportPrice":0.79853,"importCost":0.0061,"exportRevenue":0,"descriptor":"extremelyLow","spikeStatus":"none","period":"offPeak","renewables":72.51436620139592},{"nemTime":"2025-12-31T12:05:00+10:00","hour":12,"minute":5,"importKwh":0.002,"exportKwh":0,"importPrice":2.84403,"exportPrice":0.98992,"importCost":0.0057,"exportRevenue":0,"descriptor":"extremelyLow","spikeStatus":"none","period":"offPeak","renewables":71.20651335955705},{"nemTime":"2025-12-31T12:10:00+10:00","hour":12,"minute":10,"importKwh":0.002,"exportKwh":0,"importPrice":2.93139,"exportPrice":0.9105,"importCost":0.0059,"exportRevenue":0,"descriptor":"extremelyLow","spikeStatus":"none","period":"offPeak","renewables":72.01445337665612},{"nemTime":"2025-12-31T12:15:00+10:00","hour":12,"minute":15,"importKwh":0.002,"exportKwh":0,"importPrice":2.76216,"exportPrice":1.06435,"importCost":0.0055,"exportRevenue":0,"descriptor":"extremelyLow","spikeStatus":"none","period":"offPeak","renewables":71.21079979658613},{"nemTime":"2025-12-31T12:20:00+10:00","hour":12,"minute":20,"importKwh":0.011,"exportKwh":0,"importPrice":3.08029,"exportPrice":0.77513,"importCost":0.0339,"exportRevenue":0,"descriptor":"extremelyLow","spikeStatus":"none","period":"offPeak","renewables":71.04924986896744},{"nemTime":"2025-12-31T12:25:00+10:00","hour":12,"minute":25,"importKwh":0.011,"exportKwh":0,"importPrice":3.08146,"exportPrice":0.77407,"importCost":0.0339,"exportRevenue":0,"descriptor":"extremelyLow","spikeStatus":"none","period":"offPeak","renewables":72.75641805633074},{"nemTime":"2025-12-31T12:30:00+10:00","hour":12,"minute":30,"importKwh":0.011,"exportKwh":0,"importPrice":3.17386,"exportPrice":0.69007,"importCost":0.0349,"exportRevenue":0,"descriptor":"extremelyLow","spikeStatus":"none","period":"offPeak","renewables":74.74096858628891},{"nemTime":"2025-12-31T12:35:00+10:00","hour":12,"minute":35,"importKwh":0.012,"exportKwh":0,"importPrice":3.17269,"exportPrice":0.69113,"importCost":0.0381,"exportRevenue":0,"descriptor":"extremelyLow","spikeStatus":"none","period":"offPeak","renewables":74.22658260319541},{"nemTime":"2025-12-31T12:40:00+10:00","hour":12,"minute":40,"importKwh":0.001,"exportKwh":0.235,"importPrice":3.93294,"exportPrice":0,"importCost":0.0039,"exportRevenue":0,"descriptor":"extremelyLow","spikeStatus":"none","period":"offPeak","renewables":74.55457073503324},{"nemTime":"2025-12-31T12:45:00+10:00","hour":12,"minute":45,"importKwh":0,"exportKwh":0.67,"importPrice":3.93294,"exportPrice":0,"importCost":0,"exportRevenue":0,"descriptor":"extremelyLow","spikeStatus":"none","period":"offPeak","renewables":75.93629396333209},{"nemTime":"2025-12-31T12:50:00+10:00","hour":12,"minute":50,"importKwh":0,"exportKwh":0.728,"importPrice":3.93294,"exportPrice":0,"importCost":0,"exportRevenue":0,"descriptor":"extremelyLow","spikeStatus":"none","period":"offPeak","renewables":75.89613106609903},{"nemTime":"2025-12-31T12:55:00+10:00","hour":12,"minute":55,"importKwh":0,"exportKwh":0.73,"importPrice":3.93294,"exportPrice":0,"importCost":0,"exportRevenue":0,"descriptor":"extremelyLow","spikeStatus":"none","period":"offPeak","renewables":73.88092645741328},{"nemTime":"2025-12-31T13:00:00+10:00","hour":13,"minute":0,"importKwh":0.016,"exportKwh":0.133,"importPrice":3.35909,"exportPrice":0.52169,"importCost":0.0537,"exportRevenue":0.0694,"descriptor":"extremelyLow","spikeStatus":"none","period":"offPeak","renewables":73.12479566949351},{"nemTime":"2025-12-31T13:05:00+10:00","hour":13,"minute":5,"importKwh":0.002,"exportKwh":0.225,"importPrice":3.93294,"exportPrice":0,"importCost":0.0079,"exportRevenue":0,"descriptor":"extremelyLow","spikeStatus":"none","period":"offPeak","renewables":74.11047993172859},{"nemTime":"2025-12-31T13:10:00+10:00","hour":13,"minute":10,"importKwh":0.015,"exportKwh":0.106,"importPrice":3.17386,"exportPrice":0.69007,"importCost":0.0476,"exportRevenue":0.0731,"descriptor":"extremelyLow","spikeStatus":"none","period":"offPeak","renewables":74.41684380782586},{"nemTime":"2025-12-31T13:15:00+10:00","hour":13,"minute":15,"importKwh":0.001,"exportKwh":0.234,"importPrice":3.93299,"exportPrice":0.00005,"importCost":0.0039,"exportRevenue":0,"descriptor":"extremelyLow","spikeStatus":"none","period":"offPeak","renewables":73.05844735698899},{"nemTime":"2025-12-31T13:20:00+10:00","hour":13,"minute":20,"importKwh":0,"exportKwh":0.697,"importPrice":3.93411,"exportPrice":0.00106,"importCost":0,"exportRevenue":0.0007,"descriptor":"extremelyLow","spikeStatus":"none","period":"offPeak","renewables":72.04385333471907},{"nemTime":"2025-12-31T13:25:00+10:00","hour":13,"minute":25,"importKwh":0,"exportKwh":0.699,"importPrice":5.56338,"exportPrice":1.48222,"importCost":0,"exportRevenue":1.0361,"descriptor":"extremelyLow","spikeStatus":"none","period":"offPeak","renewables":71.864296576586},{"nemTime":"2025-12-31T13:30:00+10:00","hour":13,"minute":30,"importKwh":0,"exportKwh":0.693,"importPrice":3.99053,"exportPrice":0.05235,"importCost":0,"exportRevenue":0.0363,"descriptor":"extremelyLow","spikeStatus":"none","period":"offPeak","renewables":72.15947088084985},{"nemTime":"2025-12-31T13:35:00+10:00","hour":13,"minute":35,"importKwh":0,"exportKwh":0.703,"importPrice":9.16462,"exportPrice":4.75607,"importCost":0,"exportRevenue":3.3435,"descriptor":"extremelyLow","spikeStatus":"none","period":"offPeak","renewables":68.72870809377493},{"nemTime":"2025-12-31T13:40:00+10:00","hour":13,"minute":40,"importKwh":0,"exportKwh":0.697,"importPrice":9.16462,"exportPrice":4.75607,"importCost":0,"exportRevenue":3.315,"descriptor":"extremelyLow","spikeStatus":"none","period":"offPeak","renewables":67.22604685789445},{"nemTime":"2025-12-31T13:45:00+10:00","hour":13,"minute":45,"importKwh":0,"exportKwh":0.694,"importPrice":7.99734,"exportPrice":3.69491,"importCost":0,"exportRevenue":2.5643,"descriptor":"extremelyLow","spikeStatus":"none","period":"offPeak","renewables":64.97008442235447},{"nemTime":"2025-12-31T13:50:00+10:00","hour":13,"minute":50,"importKwh":0,"exportKwh":0.611,"importPrice":6.06502,"exportPrice":1.93825,"importCost":0,"exportRevenue":1.1843,"descriptor":"extremelyLow","spikeStatus":"none","period":"offPeak","renewables":64.9314048314332},{"nemTime":"2025-12-31T13:55:00+10:00","hour":13,"minute":55,"importKwh":0,"exportKwh":0.228,"importPrice":7.89022,"exportPrice":3.59753,"importCost":0,"exportRevenue":0.8202,"descriptor":"extremelyLow","spikeStatus":"none","period":"offPeak","renewables":62.920185950471584},{"nemTime":"2025-12-31T14:00:00+10:00","hour":14,"minute":0,"importKwh":0,"exportKwh":0.304,"importPrice":4.46685,"exportPrice":0.48537,"importCost":0,"exportRevenue":0.1476,"descriptor":"extremelyLow","spikeStatus":"none","period":"offPeak","renewables":64.22610727680997},{"nemTime":"2025-12-31T14:05:00+10:00","hour":14,"minute":5,"importKwh":0,"exportKwh":0.28,"importPrice":3.99006,"exportPrice":0.05193,"importCost":0,"exportRevenue":0.0145,"descriptor":"extremelyLow","spikeStatus":"none","period":"offPeak","renewables":66.2645970164148},{"nemTime":"2025-12-31T14:10:00+10:00","hour":14,"minute":10,"importKwh":0.01,"exportKwh":0.066,"importPrice":3.17152,"exportPrice":0.6922,"importCost":0.0317,"exportRevenue":0.0457,"descriptor":"extremelyLow","spikeStatus":"none","period":"offPeak","renewables":66.32801727559199},{"nemTime":"2025-12-31T14:15:00+10:00","hour":14,"minute":15,"importKwh":0,"exportKwh":0.221,"importPrice":3.93294,"exportPrice":0,"importCost":0,"exportRevenue":0,"descriptor":"extremelyLow","spikeStatus":"none","period":"offPeak","renewables":66.74869552153608},{"nemTime":"2025-12-31T14:20:00+10:00","hour":14,"minute":20,"importKwh":0.016,"exportKwh":0.087,"importPrice":3.93293,"exportPrice":0.00001,"importCost":0.0629,"exportRevenue":0,"descriptor":"extremelyLow","spikeStatus":"none","period":"offPeak","renewables":66.88790626456212},{"nemTime":"2025-12-31T14:25:00+10:00","hour":14,"minute":25,"importKwh":0.002,"exportKwh":0.22,"importPrice":3.93294,"exportPrice":0,"importCost":0.0079,"exportRevenue":0,"descriptor":"extremelyLow","spikeStatus":"none","period":"offPeak","renewables":66.20134152782187},{"nemTime":"2025-12-31T14:30:00+10:00","hour":14,"minute":30,"importKwh":0,"exportKwh":0.476,"importPrice":8.26341,"exportPrice":3.93679,"importCost":0,"exportRevenue":1.8739,"descriptor":"extremelyLow","spikeStatus":"none","period":"offPeak","renewables":66.03815774710165},{"nemTime":"2025-12-31T14:35:00+10:00","hour":14,"minute":35,"importKwh":0,"exportKwh":0.57,"importPrice":8.20869,"exportPrice":3.88705,"importCost":0,"exportRevenue":2.2156,"descriptor":"extremelyLow","spikeStatus":"none","period":"offPeak","renewables":63.243397632908746},{"nemTime":"2025-12-31T14:40:00+10:00","hour":14,"minute":40,"importKwh":0,"exportKwh":0.513,"importPrice":12.12023,"exportPrice":7.44299,"importCost":0,"exportRevenue":3.8183,"descriptor":"extremelyLow","spikeStatus":"none","period":"offPeak","renewables":63.62122571985782},{"nemTime":"2025-12-31T14:45:00+10:00","hour":14,"minute":45,"importKwh":0,"exportKwh":0.573,"importPrice":15.11928,"exportPrice":10.1694,"importCost":0,"exportRevenue":5.8271,"descriptor":"veryLow","spikeStatus":"none","period":"offPeak","renewables":59.093124895542594},{"nemTime":"2025-12-31T14:50:00+10:00","hour":14,"minute":50,"importKwh":0,"exportKwh":0.532,"importPrice":11.36466,"exportPrice":6.75611,"importCost":0,"exportRevenue":3.5942,"descriptor":"extremelyLow","spikeStatus":"none","period":"offPeak","renewables":57.454145751715934},{"nemTime":"2025-12-31T14:55:00+10:00","hour":14,"minute":55,"importKwh":0,"exportKwh":0.504,"importPrice":11.367,"exportPrice":6.75824,"importCost":0,"exportRevenue":3.4062,"descriptor":"extremelyLow","spikeStatus":"none","period":"offPeak","renewables":57.23680374440839},{"nemTime":"2025-12-31T15:00:00+10:00","hour":15,"minute":0,"importKwh":0,"exportKwh":0.486,"importPrice":11.367,"exportPrice":6.75824,"importCost":0,"exportRevenue":3.2845,"descriptor":"extremelyLow","spikeStatus":"none","period":"offPeak","renewables":55.59166830042652},{"nemTime":"2025-12-31T15:05:00+10:00","hour":15,"minute":5,"importKwh":0,"exportKwh":0.456,"importPrice":12.81615,"exportPrice":8.07564,"importCost":0,"exportRevenue":3.6825,"descriptor":"extremelyLow","spikeStatus":"none","period":"offPeak","renewables":53.37495860364797},{"nemTime":"2025-12-31T15:10:00+10:00","hour":15,"minute":10,"importKwh":0,"exportKwh":0.442,"importPrice":14.89572,"exportPrice":9.96616,"importCost":0,"exportRevenue":4.405,"descriptor":"veryLow","spikeStatus":"none","period":"offPeak","renewables":52.302295621852004},{"nemTime":"2025-12-31T15:15:00+10:00","hour":15,"minute":15,"importKwh":0,"exportKwh":0.417,"importPrice":10.50166,"exportPrice":5.97156,"importCost":0,"exportRevenue":2.4901,"descriptor":"extremelyLow","spikeStatus":"none","period":"offPeak","renewables":50.40711431872005},{"nemTime":"2025-12-31T15:20:00+10:00","hour":15,"minute":20,"importKwh":0,"exportKwh":0.346,"importPrice":11.36934,"exportPrice":6.76036,"importCost":0,"exportRevenue":2.3391,"descriptor":"extremelyLow","spikeStatus":"none","period":"offPeak","renewables":49.936797435227206},{"nemTime":"2025-12-31T15:25:00+10:00","hour":15,"minute":25,"importKwh":0,"exportKwh":0.179,"importPrice":10.36464,"exportPrice":5.847,"importCost":0,"exportRevenue":1.0466,"descriptor":"extremelyLow","spikeStatus":"none","period":"offPeak","renewables":48.3216872898112},{"nemTime":"2025-12-31T15:30:00+10:00","hour":15,"minute":30,"importKwh":0.003,"exportKwh":0.145,"importPrice":10.24885,"exportPrice":5.74174,"importCost":0.0307,"exportRevenue":0.8326,"descriptor":"extremelyLow","spikeStatus":"none","period":"offPeak","renewables":47.130451642829534},{"nemTime":"2025-12-31T15:35:00+10:00","hour":15,"minute":35,"importKwh":0,"exportKwh":0.338,"importPrice":8.11197,"exportPrice":3.79911,"importCost":0,"exportRevenue":1.2841,"descriptor":"extremelyLow","spikeStatus":"none","period":"offPeak","renewables":44.046167953108025},{"nemTime":"2025-12-31T15:40:00+10:00","hour":15,"minute":40,"importKwh":0,"exportKwh":0.209,"importPrice":4.55283,"exportPrice":0.56354,"importCost":0,"exportRevenue":0.1178,"descriptor":"extremelyLow","spikeStatus":"none","period":"offPeak","renewables":44.2199780843323},{"nemTime":"2025-12-31T15:45:00+10:00","hour":15,"minute":45,"importKwh":0,"exportKwh":0.249,"importPrice":9.39534,"exportPrice":4.96582,"importCost":0,"exportRevenue":1.2365,"descriptor":"extremelyLow","spikeStatus":"none","period":"offPeak","renewables":41.89702158019025},{"nemTime":"2025-12-31T15:50:00+10:00","hour":15,"minute":50,"importKwh":0,"exportKwh":0.337,"importPrice":10.36113,"exportPrice":5.84381,"importCost":0,"exportRevenue":1.9694,"descriptor":"extremelyLow","spikeStatus":"none","period":"offPeak","renewables":41.05629086457577},{"nemTime":"2025-12-31T15:55:00+10:00","hour":15,"minute":55,"importKwh":0,"exportKwh":0.31,"importPrice":11.367,"exportPrice":6.75824,"importCost":0,"exportRevenue":2.0951,"descriptor":"extremelyLow","spikeStatus":"none","period":"offPeak","renewables":42.87990167755309},{"nemTime":"2025-12-31T16:00:00+10:00","hour":16,"minute":0,"importKwh":0,"exportKwh":0.246,"importPrice":11.63414,"exportPrice":7.00109,"importCost":0,"exportRevenue":1.7223,"descriptor":"extremelyLow","spikeStatus":"none","period":"offPeak","renewables":43.26893899937188},{"nemTime":"2025-12-31T16:05:00+10:00","hour":16,"minute":5,"importKwh":0,"exportKwh":0.208,"importPrice":32.14242,"exportPrice":6.75398,"importCost":0,"exportRevenue":1.4048,"descriptor":"low","spikeStatus":"none","period":"peak","renewables":39.8221067863729},{"nemTime":"2025-12-31T16:10:00+10:00","hour":16,"minute":10,"importKwh":0,"exportKwh":0.219,"importPrice":32.17869,"exportPrice":6.78695,"importCost":0,"exportRevenue":1.4863,"descriptor":"low","spikeStatus":"none","period":"peak","renewables":39.39866217487019},{"nemTime":"2025-12-31T16:15:00+10:00","hour":16,"minute":15,"importKwh":0,"exportKwh":0.199,"importPrice":31.11784,"exportPrice":5.82255,"importCost":0,"exportRevenue":1.1587,"descriptor":"low","spikeStatus":"none","period":"peak","renewables":39.12075680117409},{"nemTime":"2025-12-31T16:20:00+10:00","hour":16,"minute":20,"importKwh":0,"exportKwh":0.206,"importPrice":30.88626,"exportPrice":5.61201,"importCost":0,"exportRevenue":1.1561,"descriptor":"low","spikeStatus":"none","period":"peak","renewables":38.94575730936934},{"nemTime":"2025-12-31T16:25:00+10:00","hour":16,"minute":25,"importKwh":0,"exportKwh":0.169,"importPrice":29.96928,"exportPrice":4.7784,"importCost":0,"exportRevenue":0.8075,"descriptor":"veryLow","spikeStatus":"none","period":"peak","renewables":38.27169384288162},{"nemTime":"2025-12-31T16:30:00+10:00","hour":16,"minute":30,"importKwh":0,"exportKwh":0.149,"importPrice":31.14123,"exportPrice":5.84381,"importCost":0,"exportRevenue":0.8707,"descriptor":"low","spikeStatus":"none","period":"peak","renewables":37.255663686740164},{"nemTime":"2025-12-31T16:35:00+10:00","hour":16,"minute":35,"importKwh":0,"exportKwh":0.116,"importPrice":32.45673,"exportPrice":7.03972,"importCost":0,"exportRevenue":0.8166,"descriptor":"low","spikeStatus":"none","period":"peak","renewables":31.391530934788758},{"nemTime":"2025-12-31T16:40:00+10:00","hour":16,"minute":40,"importKwh":0,"exportKwh":0.1,"importPrice":33.59625,"exportPrice":8.07564,"importCost":0,"exportRevenue":0.8076,"descriptor":"low","spikeStatus":"none","period":"peak","renewables":28.946151651954565},{"nemTime":"2025-12-31T16:45:00+10:00","hour":16,"minute":45,"importKwh":0,"exportKwh":0.075,"importPrice":35.70155,"exportPrice":9.98956,"importCost":0,"exportRevenue":0.7492,"descriptor":"low","spikeStatus":"none","period":"peak","renewables":27.960011637147673},{"nemTime":"2025-12-31T16:50:00+10:00","hour":16,"minute":50,"importKwh":0,"exportKwh":0.045,"importPrice":36.86415,"exportPrice":11.04646,"importCost":0,"exportRevenue":0.4971,"descriptor":"low","spikeStatus":"none","period":"peak","renewables":25.5151614928893},{"nemTime":"2025-12-31T16:55:00+10:00","hour":16,"minute":55,"importKwh":0.005,"exportKwh":0.013,"importPrice":38.63143,"exportPrice":12.65308,"importCost":0.1932,"exportRevenue":0.1645,"descriptor":"low","spikeStatus":"none","period":"peak","renewables":24.953275613912005},{"nemTime":"2025-12-31T17:00:00+10:00","hour":17,"minute":0,"importKwh":0.022,"exportKwh":0,"importPrice":36.86415,"exportPrice":11.04646,"importCost":0.811,"exportRevenue":0,"descriptor":"low","spikeStatus":"none","period":"peak","renewables":25.075081866603206},{"nemTime":"2025-12-31T17:05:00+10:00","hour":17,"minute":5,"importKwh":0.026,"exportKwh":0,"importPrice":33.57052,"exportPrice":8.05225,"importCost":0.8728,"exportRevenue":0,"descriptor":"low","spikeStatus":"none","period":"peak","renewables":20.219237857513022},{"nemTime":"2025-12-31T17:10:00+10:00","hour":17,"minute":10,"importKwh":0.024,"exportKwh":0,"importPrice":36.86415,"exportPrice":11.04646,"importCost":0.8847,"exportRevenue":0,"descriptor":"low","spikeStatus":"none","period":"peak","renewables":19.181758642594765},{"nemTime":"2025-12-31T17:15:00+10:00","hour":17,"minute":15,"importKwh":0.011,"exportKwh":0,"importPrice":36.86415,"exportPrice":11.04646,"importCost":0.4055,"exportRevenue":0,"descriptor":"low","spikeStatus":"none","period":"peak","renewables":17.282540172535317},{"nemTime":"2025-12-31T17:20:00+10:00","hour":17,"minute":20,"importKwh":0.001,"exportKwh":0.001,"importPrice":35.67699,"exportPrice":9.96723,"importCost":0.0357,"exportRevenue":0.01,"descriptor":"low","spikeStatus":"none","period":"peak","renewables":16.552554569621496},{"nemTime":"2025-12-31T17:25:00+10:00","hour":17,"minute":25,"importKwh":0.011,"exportKwh":0,"importPrice":35.91208,"exportPrice":10.18095,"importCost":0.395,"exportRevenue":0,"descriptor":"low","spikeStatus":"none","period":"peak","renewables":18.03590134518257},{"nemTime":"2025-12-31T17:30:00+10:00","hour":17,"minute":30,"importKwh":0.02,"exportKwh":0,"importPrice":35.70155,"exportPrice":9.98956,"importCost":0.714,"exportRevenue":0,"descriptor":"low","spikeStatus":"none","period":"peak","renewables":18.635446663479737},{"nemTime":"2025-12-31T17:35:00+10:00","hour":17,"minute":35,"importKwh":0.021,"exportKwh":0,"importPrice":33.28513,"exportPrice":7.79281,"importCost":0.699,"exportRevenue":0,"descriptor":"low","spikeStatus":"none","period":"peak","renewables":15.400584050139548},{"nemTime":"2025-12-31T17:40:00+10:00","hour":17,"minute":40,"importKwh":0.028,"exportKwh":0,"importPrice":33.57052,"exportPrice":8.05225,"importCost":0.94,"exportRevenue":0,"descriptor":"low","spikeStatus":"none","period":"peak","renewables":15.286660761415815},{"nemTime":"2025-12-31T17:45:00+10:00","hour":17,"minute":45,"importKwh":0.026,"exportKwh":0,"importPrice":35.67699,"exportPrice":9.96723,"importCost":0.9276,"exportRevenue":0,"descriptor":"low","spikeStatus":"none","period":"peak","renewables":14.480520859596371},{"nemTime":"2025-12-31T17:50:00+10:00","hour":17,"minute":50,"importKwh":0.021,"exportKwh":0,"importPrice":34.63136,"exportPrice":9.01665,"importCost":0.7273,"exportRevenue":0,"descriptor":"low","spikeStatus":"none","period":"peak","renewables":13.36284793696773},{"nemTime":"2025-12-31T17:55:00+10:00","hour":17,"minute":55,"importKwh":0.033,"exportKwh":0,"importPrice":33.45005,"exportPrice":7.94273,"importCost":1.1039,"exportRevenue":0,"descriptor":"low","spikeStatus":"none","period":"peak","renewables":14.199893557620547},{"nemTime":"2025-12-31T18:00:00+10:00","hour":18,"minute":0,"importKwh":0.047,"exportKwh":0,"importPrice":34.06877,"exportPrice":8.50521,"importCost":1.6012,"exportRevenue":0,"descriptor":"low","spikeStatus":"none","period":"peak","renewables":14.280309641529668},{"nemTime":"2025-12-31T18:05:00+10:00","hour":18,"minute":5,"importKwh":0.051,"exportKwh":0,"importPrice":34.06877,"exportPrice":8.50521,"importCost":1.7375,"exportRevenue":0,"descriptor":"low","spikeStatus":"none","period":"peak","renewables":12.790355501777736},{"nemTime":"2025-12-31T18:10:00+10:00","hour":18,"minute":10,"importKwh":0.05,"exportKwh":0,"importPrice":34.06877,"exportPrice":8.50521,"importCost":1.7034,"exportRevenue":0,"descriptor":"low","spikeStatus":"none","period":"peak","renewables":13.693205552171264},{"nemTime":"2025-12-31T18:15:00+10:00","hour":18,"minute":15,"importKwh":0.051,"exportKwh":0,"importPrice":33.93312,"exportPrice":8.38189,"importCost":1.7306,"exportRevenue":0,"descriptor":"low","spikeStatus":"none","period":"peak","renewables":13.097706737455479},{"nemTime":"2025-12-31T18:20:00+10:00","hour":18,"minute":20,"importKwh":0.054,"exportKwh":0,"importPrice":33.28513,"exportPrice":7.79281,"importCost":1.7974,"exportRevenue":0,"descriptor":"low","spikeStatus":"none","period":"peak","renewables":12.048569159911958},{"nemTime":"2025-12-31T18:25:00+10:00","hour":18,"minute":25,"importKwh":0.053,"exportKwh":0,"importPrice":33.53894,"exportPrice":8.02354,"importCost":1.7776,"exportRevenue":0,"descriptor":"low","spikeStatus":"none","period":"peak","renewables":11.503594589158547},{"nemTime":"2025-12-31T18:30:00+10:00","hour":18,"minute":30,"importKwh":0.048,"exportKwh":0,"importPrice":34.06877,"exportPrice":8.50521,"importCost":1.6353,"exportRevenue":0,"descriptor":"low","spikeStatus":"none","period":"peak","renewables":11.185923948454265},{"nemTime":"2025-12-31T18:35:00+10:00","hour":18,"minute":35,"importKwh":0.057,"exportKwh":0,"importPrice":33.93311,"exportPrice":8.38188,"importCost":1.9342,"exportRevenue":0,"descriptor":"low","spikeStatus":"none","period":"peak","renewables":10.670915036844766},{"nemTime":"2025-12-31T18:40:00+10:00","hour":18,"minute":40,"importKwh":0.063,"exportKwh":0,"importPrice":33.57052,"exportPrice":8.05225,"importCost":2.1149,"exportRevenue":0,"descriptor":"low","spikeStatus":"none","period":"peak","renewables":10.574566910685459},{"nemTime":"2025-12-31T18:45:00+10:00","hour":18,"minute":45,"importKwh":0.061,"exportKwh":0,"importPrice":32.33926,"exportPrice":6.93292,"importCost":1.9727,"exportRevenue":0,"descriptor":"low","spikeStatus":"none","period":"peak","renewables":10.653423932631087},{"nemTime":"2025-12-31T18:50:00+10:00","hour":18,"minute":50,"importKwh":0.056,"exportKwh":0,"importPrice":32.42714,"exportPrice":7.01281,"importCost":1.8159,"exportRevenue":0,"descriptor":"low","spikeStatus":"none","period":"peak","renewables":10.228642097619632},{"nemTime":"2025-12-31T18:55:00+10:00","hour":18,"minute":55,"importKwh":0.056,"exportKwh":0,"importPrice":33.28513,"exportPrice":7.79281,"importCost":1.864,"exportRevenue":0,"descriptor":"low","spikeStatus":"none","period":"peak","renewables":9.749839496401163},{"nemTime":"2025-12-31T19:00:00+10:00","hour":19,"minute":0,"importKwh":0.056,"exportKwh":0,"importPrice":33.5366,"exportPrice":8.02142,"importCost":1.878,"exportRevenue":0,"descriptor":"low","spikeStatus":"none","period":"peak","renewables":9.505313350106691},{"nemTime":"2025-12-31T19:05:00+10:00","hour":19,"minute":5,"importKwh":0.056,"exportKwh":0,"importPrice":34.06877,"exportPrice":8.50521,"importCost":1.9079,"exportRevenue":0,"descriptor":"low","spikeStatus":"none","period":"peak","renewables":8.987386628215452},{"nemTime":"2025-12-31T19:10:00+10:00","hour":19,"minute":10,"importKwh":0.056,"exportKwh":0,"importPrice":34.06877,"exportPrice":8.50521,"importCost":1.9079,"exportRevenue":0,"descriptor":"low","spikeStatus":"none","period":"peak","renewables":8.886178873056652},{"nemTime":"2025-12-31T19:15:00+10:00","hour":19,"minute":15,"importKwh":0.059,"exportKwh":0,"importPrice":33.5366,"exportPrice":8.02142,"importCost":1.9787,"exportRevenue":0,"descriptor":"low","spikeStatus":"none","period":"peak","renewables":8.801650786490086},{"nemTime":"2025-12-31T19:20:00+10:00","hour":19,"minute":20,"importKwh":0.054,"exportKwh":0,"importPrice":34.79393,"exportPrice":9.16445,"importCost":1.8789,"exportRevenue":0,"descriptor":"low","spikeStatus":"none","period":"peak","renewables":8.28208124885608},{"nemTime":"2025-12-31T19:25:00+10:00","hour":19,"minute":25,"importKwh":0.053,"exportKwh":0,"importPrice":34.06877,"exportPrice":8.50521,"importCost":1.8056,"exportRevenue":0,"descriptor":"low","spikeStatus":"none","period":"peak","renewables":7.961777215683457},{"nemTime":"2025-12-31T19:30:00+10:00","hour":19,"minute":30,"importKwh":0.051,"exportKwh":0,"importPrice":34.77191,"exportPrice":9.14443,"importCost":1.7734,"exportRevenue":0,"descriptor":"low","spikeStatus":"none","period":"peak","renewables":8.194220416689065},{"nemTime":"2025-12-31T19:35:00+10:00","hour":19,"minute":35,"importKwh":0.051,"exportKwh":0,"importPrice":33.28513,"exportPrice":7.79281,"importCost":1.6975,"exportRevenue":0,"descriptor":"low","spikeStatus":"none","period":"peak","renewables":8.240715427153912},{"nemTime":"2025-12-31T19:40:00+10:00","hour":19,"minute":40,"importKwh":0.051,"exportKwh":0,"importPrice":32.28628,"exportPrice":6.88477,"importCost":1.6466,"exportRevenue":0,"descriptor":"low","spikeStatus":"none","period":"peak","renewables":8.525290068931223},{"nemTime":"2025-12-31T19:45:00+10:00","hour":19,"minute":45,"importKwh":0.055,"exportKwh":0,"importPrice":34.34948,"exportPrice":8.7604,"importCost":1.8892,"exportRevenue":0,"descriptor":"low","spikeStatus":"none","period":"peak","renewables":8.66283968946415},{"nemTime":"2025-12-31T19:50:00+10:00","hour":19,"minute":50,"importKwh":0.055,"exportKwh":0,"importPrice":33.93312,"exportPrice":8.38189,"importCost":1.8663,"exportRevenue":0,"descriptor":"low","spikeStatus":"none","period":"peak","renewables":8.73346163104717},{"nemTime":"2025-12-31T19:55:00+10:00","hour":19,"minute":55,"importKwh":0.061,"exportKwh":0,"importPrice":33.93312,"exportPrice":8.38189,"importCost":2.0699,"exportRevenue":0,"descriptor":"low","spikeStatus":"none","period":"peak","renewables":8.934455539505729},{"nemTime":"2025-12-31T20:00:00+10:00","hour":20,"minute":0,"importKwh":0.061,"exportKwh":0,"importPrice":33.12256,"exportPrice":7.64501,"importCost":2.0205,"exportRevenue":0,"descriptor":"low","spikeStatus":"none","period":"peak","renewables":9.484729735293454},{"nemTime":"2025-12-31T20:05:00+10:00","hour":20,"minute":5,"importKwh":0.057,"exportKwh":0,"importPrice":34.78808,"exportPrice":9.15913,"importCost":1.9829,"exportRevenue":0,"descriptor":"low","spikeStatus":"none","period":"peak","renewables":9.697510210597738},{"nemTime":"2025-12-31T20:10:00+10:00","hour":20,"minute":10,"importKwh":0.046,"exportKwh":0,"importPrice":34.06877,"exportPrice":8.50521,"importCost":1.5672,"exportRevenue":0,"descriptor":"low","spikeStatus":"none","period":"peak","renewables":10.218909405232885},{"nemTime":"2025-12-31T20:15:00+10:00","hour":20,"minute":15,"importKwh":0.049,"exportKwh":0,"importPrice":33.28513,"exportPrice":7.79281,"importCost":1.631,"exportRevenue":0,"descriptor":"low","spikeStatus":"none","period":"peak","renewables":10.580220387007323},{"nemTime":"2025-12-31T20:20:00+10:00","hour":20,"minute":20,"importKwh":0.052,"exportKwh":0,"importPrice":32.14476,"exportPrice":6.75611,"importCost":1.6715,"exportRevenue":0,"descriptor":"low","spikeStatus":"none","period":"peak","renewables":10.609054507010427},{"nemTime":"2025-12-31T20:25:00+10:00","hour":20,"minute":25,"importKwh":0.053,"exportKwh":0,"importPrice":32.28628,"exportPrice":6.88477,"importCost":1.7112,"exportRevenue":0,"descriptor":"low","spikeStatus":"none","period":"peak","renewables":10.570468054349789},{"nemTime":"2025-12-31T20:30:00+10:00","hour":20,"minute":30,"importKwh":0.053,"exportKwh":0,"importPrice":32.17868,"exportPrice":6.78694,"importCost":1.7055,"exportRevenue":0,"descriptor":"low","spikeStatus":"none","period":"peak","renewables":10.83349386527306},{"nemTime":"2025-12-31T20:35:00+10:00","hour":20,"minute":35,"importKwh":0.062,"exportKwh":0,"importPrice":33.28513,"exportPrice":7.79281,"importCost":2.0637,"exportRevenue":0,"descriptor":"low","spikeStatus":"none","period":"peak","renewables":11.08228984763705},{"nemTime":"2025-12-31T20:40:00+10:00","hour":20,"minute":40,"importKwh":0.062,"exportKwh":0,"importPrice":33.93312,"exportPrice":8.38189,"importCost":2.1039,"exportRevenue":0,"descriptor":"low","spikeStatus":"none","period":"peak","renewables":10.954882692924897},{"nemTime":"2025-12-31T20:45:00+10:00","hour":20,"minute":45,"importKwh":0.055,"exportKwh":0,"importPrice":33.53426,"exportPrice":8.01929,"importCost":1.8444,"exportRevenue":0,"descriptor":"low","spikeStatus":"none","period":"peak","renewables":11.111614568358009},{"nemTime":"2025-12-31T20:50:00+10:00","hour":20,"minute":50,"importKwh":0.054,"exportKwh":0,"importPrice":33.28513,"exportPrice":7.79281,"importCost":1.7974,"exportRevenue":0,"descriptor":"low","spikeStatus":"none","period":"peak","renewables":11.332497312350059},{"nemTime":"2025-12-31T20:55:00+10:00","hour":20,"minute":55,"importKwh":0.047,"exportKwh":0,"importPrice":33.93312,"exportPrice":8.38189,"importCost":1.5949,"exportRevenue":0,"descriptor":"low","spikeStatus":"none","period":"peak","renewables":11.50320902112813},{"nemTime":"2025-12-31T21:00:00+10:00","hour":21,"minute":0,"importKwh":0.049,"exportKwh":0,"importPrice":33.93312,"exportPrice":8.38189,"importCost":1.6627,"exportRevenue":0,"descriptor":"low","spikeStatus":"none","period":"peak","renewables":11.387652205970053},{"nemTime":"2025-12-31T21:05:00+10:00","hour":21,"minute":5,"importKwh":0.051,"exportKwh":0,"importPrice":17.98422,"exportPrice":8.38189,"importCost":0.9172,"exportRevenue":0,"descriptor":"veryLow","spikeStatus":"none","period":"shoulder","renewables":11.447092529711377},{"nemTime":"2025-12-31T21:10:00+10:00","hour":21,"minute":10,"importKwh":0.054,"exportKwh":0,"importPrice":18.11987,"exportPrice":8.50521,"importCost":0.9785,"exportRevenue":0,"descriptor":"veryLow","spikeStatus":"none","period":"shoulder","renewables":11.078703889430805},{"nemTime":"2025-12-31T21:15:00+10:00","hour":21,"minute":15,"importKwh":0.057,"exportKwh":0,"importPrice":17.98422,"exportPrice":8.38189,"importCost":1.0251,"exportRevenue":0,"descriptor":"veryLow","spikeStatus":"none","period":"shoulder","renewables":10.957929567478137},{"nemTime":"2025-12-31T21:20:00+10:00","hour":21,"minute":20,"importKwh":0.056,"exportKwh":0,"importPrice":17.64735,"exportPrice":8.07564,"importCost":0.9883,"exportRevenue":0,"descriptor":"veryLow","spikeStatus":"none","period":"shoulder","renewables":10.897824071754272},{"nemTime":"2025-12-31T21:25:00+10:00","hour":21,"minute":25,"importKwh":0.052,"exportKwh":0,"importPrice":17.98422,"exportPrice":8.38189,"importCost":0.9352,"exportRevenue":0,"descriptor":"veryLow","spikeStatus":"none","period":"shoulder","renewables":10.964538461538462},{"nemTime":"2025-12-31T21:30:00+10:00","hour":21,"minute":30,"importKwh":0.051,"exportKwh":0,"importPrice":17.98422,"exportPrice":8.38189,"importCost":0.9172,"exportRevenue":0,"descriptor":"veryLow","spikeStatus":"none","period":"shoulder","renewables":11.407789912595886},{"nemTime":"2025-12-31T21:35:00+10:00","hour":21,"minute":35,"importKwh":0.05,"exportKwh":0,"importPrice":16.14976,"exportPrice":6.7142,"importCost":0.8075,"exportRevenue":0,"descriptor":"veryLow","spikeStatus":"none","period":"shoulder","renewables":12.342395028999837},{"nemTime":"2025-12-31T21:40:00+10:00","hour":21,"minute":40,"importKwh":0.049,"exportKwh":0,"importPrice":16.33738,"exportPrice":6.88477,"importCost":0.8005,"exportRevenue":0,"descriptor":"veryLow","spikeStatus":"none","period":"shoulder","renewables":12.300852055157598},{"nemTime":"2025-12-31T21:45:00+10:00","hour":21,"minute":45,"importKwh":0.1,"exportKwh":0,"importPrice":16.21808,"exportPrice":6.77631,"importCost":1.6218,"exportRevenue":0,"descriptor":"veryLow","spikeStatus":"none","period":"shoulder","renewables":12.335151253569226},{"nemTime":"2025-12-31T21:50:00+10:00","hour":21,"minute":50,"importKwh":0.128,"exportKwh":0,"importPrice":16.22979,"exportPrice":6.78695,"importCost":2.0774,"exportRevenue":0,"descriptor":"veryLow","spikeStatus":"none","period":"shoulder","renewables":12.164652048138809},{"nemTime":"2025-12-31T21:55:00+10:00","hour":21,"minute":55,"importKwh":0.058,"exportKwh":0,"importPrice":16.21808,"exportPrice":6.77631,"importCost":0.9406,"exportRevenue":0,"descriptor":"veryLow","spikeStatus":"none","period":"shoulder","renewables":12.126070929269645},{"nemTime":"2025-12-31T22:00:00+10:00","hour":22,"minute":0,"importKwh":0.055,"exportKwh":0,"importPrice":16.1982,"exportPrice":6.75824,"importCost":0.8909,"exportRevenue":0,"descriptor":"veryLow","spikeStatus":"none","period":"shoulder","renewables":12.470765485935281},{"nemTime":"2025-12-31T22:05:00+10:00","hour":22,"minute":5,"importKwh":0.05,"exportKwh":0,"importPrice":17.59238,"exportPrice":8.02567,"importCost":0.8796,"exportRevenue":0,"descriptor":"veryLow","spikeStatus":"none","period":"shoulder","renewables":12.731897974882667},{"nemTime":"2025-12-31T22:10:00+10:00","hour":22,"minute":10,"importKwh":0.049,"exportKwh":0,"importPrice":16.19352,"exportPrice":6.75398,"importCost":0.7935,"exportRevenue":0,"descriptor":"veryLow","spikeStatus":"none","period":"shoulder","renewables":13.280300547283902},{"nemTime":"2025-12-31T22:15:00+10:00","hour":22,"minute":15,"importKwh":0.048,"exportKwh":0,"importPrice":17.59004,"exportPrice":8.02354,"importCost":0.8443,"exportRevenue":0,"descriptor":"veryLow","spikeStatus":"none","period":"shoulder","renewables":13.122758151278955},{"nemTime":"2025-12-31T22:20:00+10:00","hour":22,"minute":20,"importKwh":0.049,"exportKwh":0,"importPrice":17.62396,"exportPrice":8.05438,"importCost":0.8636,"exportRevenue":0,"descriptor":"veryLow","spikeStatus":"none","period":"shoulder","renewables":13.193380493249581},{"nemTime":"2025-12-31T22:25:00+10:00","hour":22,"minute":25,"importKwh":0.049,"exportKwh":0,"importPrice":16.2298,"exportPrice":6.78696,"importCost":0.7953,"exportRevenue":0,"descriptor":"veryLow","spikeStatus":"none","period":"shoulder","renewables":13.04504853852024},{"nemTime":"2025-12-31T22:30:00+10:00","hour":22,"minute":30,"importKwh":0.049,"exportKwh":0,"importPrice":16.21808,"exportPrice":6.77631,"importCost":0.7947,"exportRevenue":0,"descriptor":"veryLow","spikeStatus":"none","period":"shoulder","renewables":12.890419732957625},{"nemTime":"2025-12-31T22:35:00+10:00","hour":22,"minute":35,"importKwh":0.053,"exportKwh":0,"importPrice":15.9806,"exportPrice":6.56042,"importCost":0.847,"exportRevenue":0,"descriptor":"veryLow","spikeStatus":"none","period":"shoulder","renewables":12.749369001423371},{"nemTime":"2025-12-31T22:40:00+10:00","hour":22,"minute":40,"importKwh":0.049,"exportKwh":0,"importPrice":17.98422,"exportPrice":8.38189,"importCost":0.8812,"exportRevenue":0,"descriptor":"veryLow","spikeStatus":"none","period":"shoulder","renewables":12.579984574600603},{"nemTime":"2025-12-31T22:45:00+10:00","hour":22,"minute":45,"importKwh":0.049,"exportKwh":0,"importPrice":16.21808,"exportPrice":6.77631,"importCost":0.7947,"exportRevenue":0,"descriptor":"veryLow","spikeStatus":"none","period":"shoulder","renewables":12.791401193578213},{"nemTime":"2025-12-31T22:50:00+10:00","hour":22,"minute":50,"importKwh":0.049,"exportKwh":0,"importPrice":16.2298,"exportPrice":6.78696,"importCost":0.7953,"exportRevenue":0,"descriptor":"veryLow","spikeStatus":"none","period":"shoulder","renewables":12.598486396968317},{"nemTime":"2025-12-31T22:55:00+10:00","hour":22,"minute":55,"importKwh":0.05,"exportKwh":0,"importPrice":15.80235,"exportPrice":6.39837,"importCost":0.7901,"exportRevenue":0,"descriptor":"veryLow","spikeStatus":"none","period":"shoulder","renewables":12.430154734670916},{"nemTime":"2025-12-31T23:00:00+10:00","hour":23,"minute":0,"importKwh":0.049,"exportKwh":0,"importPrice":16.04424,"exportPrice":6.61827,"importCost":0.7862,"exportRevenue":0,"descriptor":"veryLow","spikeStatus":"none","period":"shoulder","renewables":12.62614273578177},{"nemTime":"2025-12-31T23:05:00+10:00","hour":23,"minute":5,"importKwh":0.048,"exportKwh":0,"importPrice":16.1668,"exportPrice":6.72969,"importCost":0.776,"exportRevenue":0,"descriptor":"veryLow","spikeStatus":"none","period":"shoulder","renewables":12.873591047347519},{"nemTime":"2025-12-31T23:10:00+10:00","hour":23,"minute":10,"importKwh":0.053,"exportKwh":0,"importPrice":17.98422,"exportPrice":8.38189,"importCost":0.9532,"exportRevenue":0,"descriptor":"veryLow","spikeStatus":"none","period":"shoulder","renewables":12.085100390537338},{"nemTime":"2025-12-31T23:15:00+10:00","hour":23,"minute":15,"importKwh":0.057,"exportKwh":0,"importPrice":16.21808,"exportPrice":6.77631,"importCost":0.9244,"exportRevenue":0,"descriptor":"veryLow","spikeStatus":"none","period":"shoulder","renewables":12.424280787930277},{"nemTime":"2025-12-31T23:20:00+10:00","hour":23,"minute":20,"importKwh":0.055,"exportKwh":0,"importPrice":16.16422,"exportPrice":6.72734,"importCost":0.889,"exportRevenue":0,"descriptor":"veryLow","spikeStatus":"none","period":"shoulder","renewables":12.865539033798395},{"nemTime":"2025-12-31T23:25:00+10:00","hour":23,"minute":25,"importKwh":0.049,"exportKwh":0,"importPrice":16.06973,"exportPrice":6.64145,"importCost":0.7874,"exportRevenue":0,"descriptor":"veryLow","spikeStatus":"none","period":"shoulder","renewables":13.526805679613146},{"nemTime":"2025-12-31T23:30:00+10:00","hour":23,"minute":30,"importKwh":0.05,"exportKwh":0,"importPrice":16.03017,"exportPrice":6.60548,"importCost":0.8015,"exportRevenue":0,"descriptor":"veryLow","spikeStatus":"none","period":"shoulder","renewables":14.145388135715681},{"nemTime":"2025-12-31T23:35:00+10:00","hour":23,"minute":35,"importKwh":0.05,"exportKwh":0,"importPrice":16.02664,"exportPrice":6.60227,"importCost":0.8013,"exportRevenue":0,"descriptor":"veryLow","spikeStatus":"none","period":"shoulder","renewables":13.965182018117222},{"nemTime":"2025-12-31T23:40:00+10:00","hour":23,"minute":40,"importKwh":0.05,"exportKwh":0,"importPrice":16.22979,"exportPrice":6.78695,"importCost":0.8115,"exportRevenue":0,"descriptor":"veryLow","spikeStatus":"none","period":"shoulder","renewables":12.831020293434586},{"nemTime":"2025-12-31T23:45:00+10:00","hour":23,"minute":45,"importKwh":0.05,"exportKwh":0,"importPrice":17.62396,"exportPrice":8.05438,"importCost":0.8812,"exportRevenue":0,"descriptor":"veryLow","spikeStatus":"none","period":"shoulder","renewables":12.091234603089957},{"nemTime":"2025-12-31T23:50:00+10:00","hour":23,"minute":50,"importKwh":0.05,"exportKwh":0,"importPrice":18.68363,"exportPrice":9.01771,"importCost":0.9342,"exportRevenue":0,"descriptor":"veryLow","spikeStatus":"none","period":"shoulder","renewables":11.225574889850904},{"nemTime":"2025-12-31T23:55:00+10:00","hour":23,"minute":55,"importKwh":0.055,"exportKwh":0,"importPrice":17.62396,"exportPrice":8.05438,"importCost":0.9693,"exportRevenue":0,"descriptor":"veryLow","spikeStatus":"none","period":"shoulder","renewables":10.805578429761546},{"nemTime":"2026-01-01T00:00:00+10:00","hour":0,"minute":0,"importKwh":0.054,"exportKwh":0,"importPrice":18.68363,"exportPrice":9.01771,"importCost":1.0089,"exportRevenue":0,"descriptor":"veryLow","spikeStatus":"none","period":"shoulder","renewables":10.757837663681883}]}