{"date":"2026-01-31","importKwh":29.74,"exportKwh":10.743,"importCost":585.1,"exportRevenue":69.47,"netCost":515.63,"avgImportPrice":19.67,"avgExportPrice":6.47,"peakImportPrice":42.05,"spikeCount":0,"highCount":0,"renewablesAvg":32.9,"intervals":[{"nemTime":"2026-01-31T00:05:00+10:00","hour":0,"minute":5,"importKwh":0.001,"exportKwh":0.006,"importPrice":19.7953,"exportPrice":10.02833,"importCost":0.0198,"exportRevenue":0.0602,"descriptor":"veryLow","spikeStatus":"none","period":"shoulder","renewables":13.114497144223842},{"nemTime":"2026-01-31T00:10:00+10:00","hour":0,"minute":10,"importKwh":0.001,"exportKwh":0.001,"importPrice":20.92226,"exportPrice":11.05284,"importCost":0.0209,"exportRevenue":0.0111,"descriptor":"veryLow","spikeStatus":"none","period":"shoulder","renewables":12.820483288879664},{"nemTime":"2026-01-31T00:15:00+10:00","hour":0,"minute":15,"importKwh":0.002,"exportKwh":0,"importPrice":20.92226,"exportPrice":11.05284,"importCost":0.0418,"exportRevenue":0,"descriptor":"veryLow","spikeStatus":"none","period":"shoulder","renewables":12.953932184496042},{"nemTime":"2026-01-31T00:20:00+10:00","hour":0,"minute":20,"importKwh":0.001,"exportKwh":0.002,"importPrice":20.03857,"exportPrice":10.24948,"importCost":0.02,"exportRevenue":0.0205,"descriptor":"veryLow","spikeStatus":"none","period":"shoulder","renewables":13.011411430919562},{"nemTime":"2026-01-31T00:25:00+10:00","hour":0,"minute":25,"importKwh":0,"exportKwh":0,"importPrice":19.47827,"exportPrice":9.74012,"importCost":0,"exportRevenue":0,"descriptor":"veryLow","spikeStatus":"none","period":"shoulder","renewables":13.128464971480488},{"nemTime":"2026-01-31T00:30:00+10:00","hour":0,"minute":30,"importKwh":0,"exportKwh":0.001,"importPrice":19.47468,"exportPrice":9.73685,"importCost":0,"exportRevenue":0.0097,"descriptor":"veryLow","spikeStatus":"none","period":"shoulder","renewables":13.016249924423642},{"nemTime":"2026-01-31T00:35:00+10:00","hour":0,"minute":35,"importKwh":0.001,"exportKwh":0,"importPrice":19.93885,"exportPrice":10.15883,"importCost":0.0199,"exportRevenue":0,"descriptor":"veryLow","spikeStatus":"none","period":"shoulder","renewables":12.921500053655471},{"nemTime":"2026-01-31T00:40:00+10:00","hour":0,"minute":40,"importKwh":0,"exportKwh":0.001,"importPrice":19.7788,"exportPrice":10.01333,"importCost":0,"exportRevenue":0.01,"descriptor":"veryLow","spikeStatus":"none","period":"shoulder","renewables":12.900268792490637},{"nemTime":"2026-01-31T00:45:00+10:00","hour":0,"minute":45,"importKwh":0.001,"exportKwh":0.001,"importPrice":19.77558,"exportPrice":10.0104,"importCost":0.0198,"exportRevenue":0.01,"descriptor":"veryLow","spikeStatus":"none","period":"shoulder","renewables":12.731087981116278},{"nemTime":"2026-01-31T00:50:00+10:00","hour":0,"minute":50,"importKwh":0,"exportKwh":0.001,"importPrice":19.52741,"exportPrice":9.78479,"importCost":0,"exportRevenue":0.0098,"descriptor":"veryLow","spikeStatus":"none","period":"shoulder","renewables":12.599806116071639},{"nemTime":"2026-01-31T00:55:00+10:00","hour":0,"minute":55,"importKwh":0.001,"exportKwh":0,"importPrice":19.51024,"exportPrice":9.76919,"importCost":0.0195,"exportRevenue":0,"descriptor":"veryLow","spikeStatus":"none","period":"shoulder","renewables":12.749385183148238},{"nemTime":"2026-01-31T01:00:00+10:00","hour":1,"minute":0,"importKwh":0,"exportKwh":0.001,"importPrice":19.66275,"exportPrice":9.90783,"importCost":0,"exportRevenue":0.0099,"descriptor":"veryLow","spikeStatus":"none","period":"shoulder","renewables":12.623230097802901},{"nemTime":"2026-01-31T01:05:00+10:00","hour":1,"minute":5,"importKwh":0,"exportKwh":0.001,"importPrice":19.51369,"exportPrice":9.77232,"importCost":0,"exportRevenue":0.0098,"descriptor":"veryLow","spikeStatus":"none","period":"shoulder","renewables":13.156746011142525},{"nemTime":"2026-01-31T01:10:00+10:00","hour":1,"minute":10,"importKwh":0.001,"exportKwh":0,"importPrice":19.51774,"exportPrice":9.776,"importCost":0.0195,"exportRevenue":0,"descriptor":"veryLow","spikeStatus":"none","period":"shoulder","renewables":13.45101043769463},{"nemTime":"2026-01-31T01:15:00+10:00","hour":1,"minute":15,"importKwh":0,"exportKwh":0.001,"importPrice":19.89886,"exportPrice":10.12248,"importCost":0,"exportRevenue":0.0101,"descriptor":"veryLow","spikeStatus":"none","period":"shoulder","renewables":13.652916646386554},{"nemTime":"2026-01-31T01:20:00+10:00","hour":1,"minute":20,"importKwh":0.001,"exportKwh":0,"importPrice":19.81396,"exportPrice":10.04529,"importCost":0.0198,"exportRevenue":0,"descriptor":"veryLow","spikeStatus":"none","period":"shoulder","renewables":13.841826571550284},{"nemTime":"2026-01-31T01:25:00+10:00","hour":1,"minute":25,"importKwh":0,"exportKwh":0.001,"importPrice":19.88646,"exportPrice":10.1112,"importCost":0,"exportRevenue":0.0101,"descriptor":"veryLow","spikeStatus":"none","period":"shoulder","renewables":13.78974945326614},{"nemTime":"2026-01-31T01:30:00+10:00","hour":1,"minute":30,"importKwh":0.001,"exportKwh":0,"importPrice":20.92226,"exportPrice":11.05284,"importCost":0.0209,"exportRevenue":0,"descriptor":"veryLow","spikeStatus":"none","period":"shoulder","renewables":14.072152392861167},{"nemTime":"2026-01-31T01:35:00+10:00","hour":1,"minute":35,"importKwh":0,"exportKwh":0.001,"importPrice":19.62776,"exportPrice":9.87602,"importCost":0,"exportRevenue":0.0099,"descriptor":"veryLow","spikeStatus":"none","period":"shoulder","renewables":14.160213687013428},{"nemTime":"2026-01-31T01:40:00+10:00","hour":1,"minute":40,"importKwh":0,"exportKwh":0.001,"importPrice":19.40177,"exportPrice":9.67057,"importCost":0,"exportRevenue":0.0097,"descriptor":"veryLow","spikeStatus":"none","period":"shoulder","renewables":14.143861503877242},{"nemTime":"2026-01-31T01:45:00+10:00","hour":1,"minute":45,"importKwh":0.001,"exportKwh":0.001,"importPrice":20.93928,"exportPrice":11.06831,"importCost":0.0209,"exportRevenue":0.0111,"descriptor":"veryLow","spikeStatus":"none","period":"shoulder","renewables":13.673380783486708},{"nemTime":"2026-01-31T01:50:00+10:00","hour":1,"minute":50,"importKwh":0.003,"exportKwh":0.003,"importPrice":20.92226,"exportPrice":11.05284,"importCost":0.0628,"exportRevenue":0.0332,"descriptor":"veryLow","spikeStatus":"none","period":"shoulder","renewables":13.443783445610036},{"nemTime":"2026-01-31T01:55:00+10:00","hour":1,"minute":55,"importKwh":0.003,"exportKwh":0.002,"importPrice":20.0812,"exportPrice":10.28823,"importCost":0.0602,"exportRevenue":0.0206,"descriptor":"veryLow","spikeStatus":"none","period":"shoulder","renewables":13.119998375397786},{"nemTime":"2026-01-31T02:00:00+10:00","hour":2,"minute":0,"importKwh":0.003,"exportKwh":0.003,"importPrice":19.3301,"exportPrice":9.60542,"importCost":0.058,"exportRevenue":0.0288,"descriptor":"veryLow","spikeStatus":"none","period":"shoulder","renewables":13.404669883888518},{"nemTime":"2026-01-31T02:05:00+10:00","hour":2,"minute":5,"importKwh":0.002,"exportKwh":0.002,"importPrice":19.44583,"exportPrice":9.71063,"importCost":0.0389,"exportRevenue":0.0194,"descriptor":"veryLow","spikeStatus":"none","period":"shoulder","renewables":12.860548390428422},{"nemTime":"2026-01-31T02:10:00+10:00","hour":2,"minute":10,"importKwh":0.003,"exportKwh":0.002,"importPrice":19.6626,"exportPrice":9.90769,"importCost":0.059,"exportRevenue":0.0198,"descriptor":"veryLow","spikeStatus":"none","period":"shoulder","renewables":12.721874316939891},{"nemTime":"2026-01-31T02:15:00+10:00","hour":2,"minute":15,"importKwh":0.002,"exportKwh":0.003,"importPrice":19.68172,"exportPrice":9.92507,"importCost":0.0394,"exportRevenue":0.0298,"descriptor":"veryLow","spikeStatus":"none","period":"shoulder","renewables":12.551468603432191},{"nemTime":"2026-01-31T02:20:00+10:00","hour":2,"minute":20,"importKwh":0.002,"exportKwh":0.002,"importPrice":19.52187,"exportPrice":9.77975,"importCost":0.039,"exportRevenue":0.0196,"descriptor":"veryLow","spikeStatus":"none","period":"shoulder","renewables":12.482968030628564},{"nemTime":"2026-01-31T02:25:00+10:00","hour":2,"minute":25,"importKwh":0.003,"exportKwh":0.004,"importPrice":19.52373,"exportPrice":9.78144,"importCost":0.0586,"exportRevenue":0.0391,"descriptor":"veryLow","spikeStatus":"none","period":"shoulder","renewables":12.192220689254071},{"nemTime":"2026-01-31T02:30:00+10:00","hour":2,"minute":30,"importKwh":0.001,"exportKwh":0.001,"importPrice":19.65988,"exportPrice":9.90522,"importCost":0.0197,"exportRevenue":0.0099,"descriptor":"veryLow","spikeStatus":"none","period":"shoulder","renewables":11.95778285589399},{"nemTime":"2026-01-31T02:35:00+10:00","hour":2,"minute":35,"importKwh":0.002,"exportKwh":0.002,"importPrice":19.60315,"exportPrice":9.85365,"importCost":0.0392,"exportRevenue":0.0197,"descriptor":"veryLow","spikeStatus":"none","period":"shoulder","renewables":11.795946442027164},{"nemTime":"2026-01-31T02:40:00+10:00","hour":2,"minute":40,"importKwh":0.002,"exportKwh":0.004,"importPrice":20.1419,"exportPrice":10.34342,"importCost":0.0403,"exportRevenue":0.0414,"descriptor":"veryLow","spikeStatus":"none","period":"shoulder","renewables":11.520336109972853},{"nemTime":"2026-01-31T02:45:00+10:00","hour":2,"minute":45,"importKwh":0.002,"exportKwh":0.002,"importPrice":19.57946,"exportPrice":9.83211,"importCost":0.0392,"exportRevenue":0.0197,"descriptor":"veryLow","spikeStatus":"none","period":"shoulder","renewables":11.838872520006161},{"nemTime":"2026-01-31T02:50:00+10:00","hour":2,"minute":50,"importKwh":0.002,"exportKwh":0.001,"importPrice":19.87531,"exportPrice":10.10107,"importCost":0.0398,"exportRevenue":0.0101,"descriptor":"veryLow","spikeStatus":"none","period":"shoulder","renewables":11.710707985312514},{"nemTime":"2026-01-31T02:55:00+10:00","hour":2,"minute":55,"importKwh":0.001,"exportKwh":0.002,"importPrice":19.50415,"exportPrice":9.76365,"importCost":0.0195,"exportRevenue":0.0195,"descriptor":"veryLow","spikeStatus":"none","period":"shoulder","renewables":11.777420175674685},{"nemTime":"2026-01-31T03:00:00+10:00","hour":3,"minute":0,"importKwh":0.004,"exportKwh":0.003,"importPrice":19.50581,"exportPrice":9.76516,"importCost":0.078,"exportRevenue":0.0293,"descriptor":"veryLow","spikeStatus":"none","period":"shoulder","renewables":12.108079640543092},{"nemTime":"2026-01-31T03:05:00+10:00","hour":3,"minute":5,"importKwh":0,"exportKwh":0,"importPrice":19.40177,"exportPrice":9.67057,"importCost":0,"exportRevenue":0,"descriptor":"veryLow","spikeStatus":"none","period":"shoulder","renewables":12.54208771257124},{"nemTime":"2026-01-31T03:10:00+10:00","hour":3,"minute":10,"importKwh":0.002,"exportKwh":0.002,"importPrice":19.43836,"exportPrice":9.70383,"importCost":0.0389,"exportRevenue":0.0194,"descriptor":"veryLow","spikeStatus":"none","period":"shoulder","renewables":12.697141058220634},{"nemTime":"2026-01-31T03:15:00+10:00","hour":3,"minute":15,"importKwh":0.002,"exportKwh":0.002,"importPrice":19.39152,"exportPrice":9.66125,"importCost":0.0388,"exportRevenue":0.0193,"descriptor":"veryLow","spikeStatus":"none","period":"shoulder","renewables":12.98049290561786},{"nemTime":"2026-01-31T03:20:00+10:00","hour":3,"minute":20,"importKwh":0.002,"exportKwh":0.002,"importPrice":19.40177,"exportPrice":9.67057,"importCost":0.0388,"exportRevenue":0.0193,"descriptor":"veryLow","spikeStatus":"none","period":"shoulder","renewables":13.215527448253292},{"nemTime":"2026-01-31T03:25:00+10:00","hour":3,"minute":25,"importKwh":0.001,"exportKwh":0.002,"importPrice":19.4158,"exportPrice":9.68333,"importCost":0.0194,"exportRevenue":0.0194,"descriptor":"veryLow","spikeStatus":"none","period":"shoulder","renewables":13.342255748934203},{"nemTime":"2026-01-31T03:30:00+10:00","hour":3,"minute":30,"importKwh":0.001,"exportKwh":0.003,"importPrice":19.40177,"exportPrice":9.67057,"importCost":0.0194,"exportRevenue":0.029,"descriptor":"veryLow","spikeStatus":"none","period":"shoulder","renewables":13.616246875537815},{"nemTime":"2026-01-31T03:35:00+10:00","hour":3,"minute":35,"importKwh":0.002,"exportKwh":0.002,"importPrice":19.37838,"exportPrice":9.64931,"importCost":0.0388,"exportRevenue":0.0193,"descriptor":"veryLow","spikeStatus":"none","period":"shoulder","renewables":13.572247799284279},{"nemTime":"2026-01-31T03:40:00+10:00","hour":3,"minute":40,"importKwh":0.002,"exportKwh":0.003,"importPrice":19.37838,"exportPrice":9.64931,"importCost":0.0388,"exportRevenue":0.0289,"descriptor":"veryLow","spikeStatus":"none","period":"shoulder","renewables":13.405337058196576},{"nemTime":"2026-01-31T03:45:00+10:00","hour":3,"minute":45,"importKwh":0.001,"exportKwh":0.002,"importPrice":19.43618,"exportPrice":9.70185,"importCost":0.0194,"exportRevenue":0.0194,"descriptor":"veryLow","spikeStatus":"none","period":"shoulder","renewables":12.901382872293766},{"nemTime":"2026-01-31T03:50:00+10:00","hour":3,"minute":50,"importKwh":0.002,"exportKwh":0.002,"importPrice":19.43742,"exportPrice":9.70298,"importCost":0.0389,"exportRevenue":0.0194,"descriptor":"veryLow","spikeStatus":"none","period":"shoulder","renewables":12.62881979452021},{"nemTime":"2026-01-31T03:55:00+10:00","hour":3,"minute":55,"importKwh":0.002,"exportKwh":0.001,"importPrice":19.40177,"exportPrice":9.67057,"importCost":0.0388,"exportRevenue":0.0097,"descriptor":"veryLow","spikeStatus":"none","period":"shoulder","renewables":12.140705751552101},{"nemTime":"2026-01-31T04:00:00+10:00","hour":4,"minute":0,"importKwh":0.001,"exportKwh":0.001,"importPrice":19.40177,"exportPrice":9.67057,"importCost":0.0194,"exportRevenue":0.0097,"descriptor":"veryLow","spikeStatus":"none","period":"shoulder","renewables":11.917330376560498},{"nemTime":"2026-01-31T04:05:00+10:00","hour":4,"minute":5,"importKwh":0.002,"exportKwh":0.002,"importPrice":19.49179,"exportPrice":9.75241,"importCost":0.039,"exportRevenue":0.0195,"descriptor":"veryLow","spikeStatus":"none","period":"shoulder","renewables":11.502604904936838},{"nemTime":"2026-01-31T04:10:00+10:00","hour":4,"minute":10,"importKwh":0.002,"exportKwh":0.002,"importPrice":19.69221,"exportPrice":9.93461,"importCost":0.0394,"exportRevenue":0.0199,"descriptor":"veryLow","spikeStatus":"none","period":"shoulder","renewables":10.816184158380022},{"nemTime":"2026-01-31T04:15:00+10:00","hour":4,"minute":15,"importKwh":0.001,"exportKwh":0.001,"importPrice":19.74403,"exportPrice":9.98172,"importCost":0.0197,"exportRevenue":0.01,"descriptor":"veryLow","spikeStatus":"none","period":"shoulder","renewables":9.981609765093708},{"nemTime":"2026-01-31T04:20:00+10:00","hour":4,"minute":20,"importKwh":0.001,"exportKwh":0.002,"importPrice":22.6062,"exportPrice":12.58369,"importCost":0.0226,"exportRevenue":0.0252,"descriptor":"veryLow","spikeStatus":"none","period":"shoulder","renewables":9.001817882349066},{"nemTime":"2026-01-31T04:25:00+10:00","hour":4,"minute":25,"importKwh":0.001,"exportKwh":0.001,"importPrice":22.7834,"exportPrice":12.74478,"importCost":0.0228,"exportRevenue":0.0127,"descriptor":"veryLow","spikeStatus":"none","period":"shoulder","renewables":7.8316761892576},{"nemTime":"2026-01-31T04:30:00+10:00","hour":4,"minute":30,"importKwh":0.003,"exportKwh":0.004,"importPrice":22.20884,"exportPrice":12.22245,"importCost":0.0666,"exportRevenue":0.0489,"descriptor":"veryLow","spikeStatus":"none","period":"shoulder","renewables":7.269598519212004},{"nemTime":"2026-01-31T04:35:00+10:00","hour":4,"minute":35,"importKwh":0.001,"exportKwh":0,"importPrice":22.75723,"exportPrice":12.72099,"importCost":0.0228,"exportRevenue":0,"descriptor":"veryLow","spikeStatus":"none","period":"shoulder","renewables":6.95663760032492},{"nemTime":"2026-01-31T04:40:00+10:00","hour":4,"minute":40,"importKwh":0.003,"exportKwh":0.002,"importPrice":22.99605,"exportPrice":12.9381,"importCost":0.069,"exportRevenue":0.0259,"descriptor":"veryLow","spikeStatus":"none","period":"shoulder","renewables":6.4505139209137825},{"nemTime":"2026-01-31T04:45:00+10:00","hour":4,"minute":45,"importKwh":0.001,"exportKwh":0.002,"importPrice":23.20358,"exportPrice":13.12677,"importCost":0.0232,"exportRevenue":0.0263,"descriptor":"veryLow","spikeStatus":"none","period":"shoulder","renewables":6.341373359632946},{"nemTime":"2026-01-31T04:50:00+10:00","hour":4,"minute":50,"importKwh":0.001,"exportKwh":0.002,"importPrice":24.03779,"exportPrice":13.88514,"importCost":0.024,"exportRevenue":0.0278,"descriptor":"veryLow","spikeStatus":"none","period":"shoulder","renewables":6.086469984994135},{"nemTime":"2026-01-31T04:55:00+10:00","hour":4,"minute":55,"importKwh":0.002,"exportKwh":0.001,"importPrice":23.40042,"exportPrice":13.30571,"importCost":0.0468,"exportRevenue":0.0133,"descriptor":"veryLow","spikeStatus":"none","period":"shoulder","renewables":6.213012533895356},{"nemTime":"2026-01-31T05:00:00+10:00","hour":5,"minute":0,"importKwh":0.001,"exportKwh":0.001,"importPrice":23.38364,"exportPrice":13.29045,"importCost":0.0234,"exportRevenue":0.0133,"descriptor":"veryLow","spikeStatus":"none","period":"shoulder","renewables":5.854645449047475},{"nemTime":"2026-01-31T05:05:00+10:00","hour":5,"minute":5,"importKwh":0.002,"exportKwh":0.003,"importPrice":24.40731,"exportPrice":14.22106,"importCost":0.0488,"exportRevenue":0.0427,"descriptor":"veryLow","spikeStatus":"none","period":"shoulder","renewables":5.522822582781252},{"nemTime":"2026-01-31T05:10:00+10:00","hour":5,"minute":10,"importKwh":0.004,"exportKwh":0.196,"importPrice":25.57536,"exportPrice":15.28292,"importCost":0.1023,"exportRevenue":2.9955,"descriptor":"veryLow","spikeStatus":"none","period":"shoulder","renewables":5.511764396958301},{"nemTime":"2026-01-31T05:15:00+10:00","hour":5,"minute":15,"importKwh":0.002,"exportKwh":0.066,"importPrice":25.11418,"exportPrice":14.86367,"importCost":0.0502,"exportRevenue":0.981,"descriptor":"veryLow","spikeStatus":"none","period":"shoulder","renewables":5.607173962082555},{"nemTime":"2026-01-31T05:20:00+10:00","hour":5,"minute":20,"importKwh":0.001,"exportKwh":0.003,"importPrice":25.26027,"exportPrice":14.99648,"importCost":0.0253,"exportRevenue":0.045,"descriptor":"veryLow","spikeStatus":"none","period":"shoulder","renewables":5.141550145994678},{"nemTime":"2026-01-31T05:25:00+10:00","hour":5,"minute":25,"importKwh":0.001,"exportKwh":0.001,"importPrice":25.0327,"exportPrice":14.7896,"importCost":0.025,"exportRevenue":0.0148,"descriptor":"veryLow","spikeStatus":"none","period":"shoulder","renewables":5.061320136633944},{"nemTime":"2026-01-31T05:30:00+10:00","hour":5,"minute":30,"importKwh":0.002,"exportKwh":0.001,"importPrice":23.67583,"exportPrice":13.55608,"importCost":0.0474,"exportRevenue":0.0136,"descriptor":"veryLow","spikeStatus":"none","period":"shoulder","renewables":4.6583221795850465},{"nemTime":"2026-01-31T05:35:00+10:00","hour":5,"minute":35,"importKwh":0.001,"exportKwh":0.002,"importPrice":23.29157,"exportPrice":13.20676,"importCost":0.0233,"exportRevenue":0.0264,"descriptor":"veryLow","spikeStatus":"none","period":"shoulder","renewables":6.504418396974347},{"nemTime":"2026-01-31T05:40:00+10:00","hour":5,"minute":40,"importKwh":0.003,"exportKwh":0.002,"importPrice":23.48094,"exportPrice":13.37891,"importCost":0.0704,"exportRevenue":0.0268,"descriptor":"veryLow","spikeStatus":"none","period":"shoulder","renewables":6.436778841492188},{"nemTime":"2026-01-31T05:45:00+10:00","hour":5,"minute":45,"importKwh":0.002,"exportKwh":0.002,"importPrice":25.25477,"exportPrice":14.99148,"importCost":0.0505,"exportRevenue":0.03,"descriptor":"veryLow","spikeStatus":"none","period":"shoulder","renewables":6.509282662133849},{"nemTime":"2026-01-31T05:50:00+10:00","hour":5,"minute":50,"importKwh":0,"exportKwh":0.478,"importPrice":25.35845,"exportPrice":15.08573,"importCost":0,"exportRevenue":7.211,"descriptor":"veryLow","spikeStatus":"none","period":"shoulder","renewables":6.264351272558404},{"nemTime":"2026-01-31T05:55:00+10:00","hour":5,"minute":55,"importKwh":0.002,"exportKwh":0.065,"importPrice":22.9845,"exportPrice":12.9276,"importCost":0.046,"exportRevenue":0.8403,"descriptor":"veryLow","spikeStatus":"none","period":"shoulder","renewables":6.920865952636119},{"nemTime":"2026-01-31T06:00:00+10:00","hour":6,"minute":0,"importKwh":0.001,"exportKwh":0.002,"importPrice":22.10043,"exportPrice":12.1239,"importCost":0.0221,"exportRevenue":0.0242,"descriptor":"veryLow","spikeStatus":"none","period":"shoulder","renewables":7.294343510787643},{"nemTime":"2026-01-31T06:05:00+10:00","hour":6,"minute":5,"importKwh":0.002,"exportKwh":0.001,"importPrice":22.086,"exportPrice":12.11078,"importCost":0.0442,"exportRevenue":0.0121,"descriptor":"veryLow","spikeStatus":"none","period":"shoulder","renewables":11.400498553412824},{"nemTime":"2026-01-31T06:10:00+10:00","hour":6,"minute":10,"importKwh":0.002,"exportKwh":0.001,"importPrice":22.19753,"exportPrice":12.21217,"importCost":0.0444,"exportRevenue":0.0122,"descriptor":"veryLow","spikeStatus":"none","period":"shoulder","renewables":11.929014452769795},{"nemTime":"2026-01-31T06:15:00+10:00","hour":6,"minute":15,"importKwh":0.001,"exportKwh":0.001,"importPrice":20.10652,"exportPrice":10.31126,"importCost":0.0201,"exportRevenue":0.0103,"descriptor":"veryLow","spikeStatus":"none","period":"shoulder","renewables":13.387116153604307},{"nemTime":"2026-01-31T06:20:00+10:00","hour":6,"minute":20,"importKwh":0.002,"exportKwh":0.002,"importPrice":19.84388,"exportPrice":10.07249,"importCost":0.0397,"exportRevenue":0.0201,"descriptor":"veryLow","spikeStatus":"none","period":"shoulder","renewables":14.782658525830792},{"nemTime":"2026-01-31T06:25:00+10:00","hour":6,"minute":25,"importKwh":0.002,"exportKwh":0.002,"importPrice":18.10117,"exportPrice":8.48821,"importCost":0.0362,"exportRevenue":0.017,"descriptor":"veryLow","spikeStatus":"none","period":"shoulder","renewables":15.783185017851126},{"nemTime":"2026-01-31T06:30:00+10:00","hour":6,"minute":30,"importKwh":0.003,"exportKwh":0.002,"importPrice":15.23602,"exportPrice":5.88353,"importCost":0.0457,"exportRevenue":0.0118,"descriptor":"veryLow","spikeStatus":"none","period":"shoulder","renewables":17.558847912943822},{"nemTime":"2026-01-31T06:35:00+10:00","hour":6,"minute":35,"importKwh":0.002,"exportKwh":0.002,"importPrice":16.19586,"exportPrice":6.75611,"importCost":0.0324,"exportRevenue":0.0135,"descriptor":"veryLow","spikeStatus":"none","period":"shoulder","renewables":25.278393722982734},{"nemTime":"2026-01-31T06:40:00+10:00","hour":6,"minute":40,"importKwh":0.001,"exportKwh":0.002,"importPrice":16.2313,"exportPrice":6.78833,"importCost":0.0162,"exportRevenue":0.0136,"descriptor":"veryLow","spikeStatus":"none","period":"shoulder","renewables":25.941771223580968},{"nemTime":"2026-01-31T06:45:00+10:00","hour":6,"minute":45,"importKwh":0.008,"exportKwh":0.007,"importPrice":14.90668,"exportPrice":5.58413,"importCost":0.1193,"exportRevenue":0.0391,"descriptor":"veryLow","spikeStatus":"none","period":"shoulder","renewables":26.32839567940391},{"nemTime":"2026-01-31T06:50:00+10:00","hour":6,"minute":50,"importKwh":0.006,"exportKwh":0.004,"importPrice":14.97521,"exportPrice":5.64643,"importCost":0.0899,"exportRevenue":0.0226,"descriptor":"veryLow","spikeStatus":"none","period":"shoulder","renewables":28.379207030648967},{"nemTime":"2026-01-31T06:55:00+10:00","hour":6,"minute":55,"importKwh":0.009,"exportKwh":0.005,"importPrice":12.59373,"exportPrice":3.48144,"importCost":0.1133,"exportRevenue":0.0174,"descriptor":"extremelyLow","spikeStatus":"none","period":"shoulder","renewables":30.681622439725693},{"nemTime":"2026-01-31T07:00:00+10:00","hour":7,"minute":0,"importKwh":0.008,"exportKwh":0.005,"importPrice":12.5432,"exportPrice":3.43551,"importCost":0.1003,"exportRevenue":0.0172,"descriptor":"extremelyLow","spikeStatus":"none","period":"shoulder","renewables":32.6329372831108},{"nemTime":"2026-01-31T07:05:00+10:00","hour":7,"minute":5,"importKwh":0.008,"exportKwh":0.007,"importPrice":12.49344,"exportPrice":3.39027,"importCost":0.0999,"exportRevenue":0.0237,"descriptor":"extremelyLow","spikeStatus":"none","period":"shoulder","renewables":39.18071161232815},{"nemTime":"2026-01-31T07:10:00+10:00","hour":7,"minute":10,"importKwh":0.007,"exportKwh":0.005,"importPrice":14.8969,"exportPrice":5.57523,"importCost":0.1043,"exportRevenue":0.0279,"descriptor":"veryLow","spikeStatus":"none","period":"shoulder","renewables":40.023433888280074},{"nemTime":"2026-01-31T07:15:00+10:00","hour":7,"minute":15,"importKwh":0.007,"exportKwh":0.006,"importPrice":14.91458,"exportPrice":5.59131,"importCost":0.1044,"exportRevenue":0.0335,"descriptor":"veryLow","spikeStatus":"none","period":"shoulder","renewables":40.70750096544894},{"nemTime":"2026-01-31T07:20:00+10:00","hour":7,"minute":20,"importKwh":0.006,"exportKwh":0.005,"importPrice":12.60617,"exportPrice":3.49275,"importCost":0.0756,"exportRevenue":0.0175,"descriptor":"extremelyLow","spikeStatus":"none","period":"shoulder","renewables":41.917082267318825},{"nemTime":"2026-01-31T07:25:00+10:00","hour":7,"minute":25,"importKwh":0.007,"exportKwh":0.008,"importPrice":12.57799,"exportPrice":3.46714,"importCost":0.088,"exportRevenue":0.0277,"descriptor":"extremelyLow","spikeStatus":"none","period":"shoulder","renewables":43.28944464430229},{"nemTime":"2026-01-31T07:30:00+10:00","hour":7,"minute":30,"importKwh":0.006,"exportKwh":0.004,"importPrice":11.05165,"exportPrice":2.07955,"importCost":0.0663,"exportRevenue":0.0083,"descriptor":"extremelyLow","spikeStatus":"none","period":"shoulder","renewables":44.74320721571408},{"nemTime":"2026-01-31T07:35:00+10:00","hour":7,"minute":35,"importKwh":0.007,"exportKwh":0.006,"importPrice":12.57544,"exportPrice":3.46482,"importCost":0.088,"exportRevenue":0.0208,"descriptor":"extremelyLow","spikeStatus":"none","period":"shoulder","renewables":47.79696571068324},{"nemTime":"2026-01-31T07:40:00+10:00","hour":7,"minute":40,"importKwh":0.006,"exportKwh":0.007,"importPrice":12.74501,"exportPrice":3.61898,"importCost":0.0765,"exportRevenue":0.0253,"descriptor":"extremelyLow","spikeStatus":"none","period":"shoulder","renewables":47.9546479088943},{"nemTime":"2026-01-31T07:45:00+10:00","hour":7,"minute":45,"importKwh":0.007,"exportKwh":0.009,"importPrice":12.76735,"exportPrice":3.63928,"importCost":0.0894,"exportRevenue":0.0328,"descriptor":"extremelyLow","spikeStatus":"none","period":"shoulder","renewables":49.22919097085714},{"nemTime":"2026-01-31T07:50:00+10:00","hour":7,"minute":50,"importKwh":0.013,"exportKwh":0.007,"importPrice":12.78345,"exportPrice":3.65392,"importCost":0.1662,"exportRevenue":0.0256,"descriptor":"extremelyLow","spikeStatus":"none","period":"shoulder","renewables":49.13173380175282},{"nemTime":"2026-01-31T07:55:00+10:00","hour":7,"minute":55,"importKwh":0.008,"exportKwh":0.006,"importPrice":12.78182,"exportPrice":3.65244,"importCost":0.1023,"exportRevenue":0.0219,"descriptor":"extremelyLow","spikeStatus":"none","period":"shoulder","renewables":50.4121443524436},{"nemTime":"2026-01-31T08:00:00+10:00","hour":8,"minute":0,"importKwh":0.005,"exportKwh":0.003,"importPrice":11.1151,"exportPrice":2.13724,"importCost":0.0556,"exportRevenue":0.0064,"descriptor":"extremelyLow","spikeStatus":"none","period":"shoulder","renewables":52.78590506919222},{"nemTime":"2026-01-31T08:05:00+10:00","hour":8,"minute":5,"importKwh":0.011,"exportKwh":0.009,"importPrice":11.22039,"exportPrice":2.23296,"importCost":0.1234,"exportRevenue":0.0201,"descriptor":"extremelyLow","spikeStatus":"none","period":"shoulder","renewables":55.805186675625976},{"nemTime":"2026-01-31T08:10:00+10:00","hour":8,"minute":10,"importKwh":0.007,"exportKwh":0.006,"importPrice":15.05081,"exportPrice":5.71515,"importCost":0.1054,"exportRevenue":0.0343,"descriptor":"veryLow","spikeStatus":"none","period":"shoulder","renewables":53.86697187119336},{"nemTime":"2026-01-31T08:15:00+10:00","hour":8,"minute":15,"importKwh":0.005,"exportKwh":0.004,"importPrice":15.10365,"exportPrice":5.76319,"importCost":0.0755,"exportRevenue":0.0231,"descriptor":"veryLow","spikeStatus":"none","period":"shoulder","renewables":54.92347923066413},{"nemTime":"2026-01-31T08:20:00+10:00","hour":8,"minute":20,"importKwh":0.007,"exportKwh":0.01,"importPrice":14.96626,"exportPrice":5.63829,"importCost":0.1048,"exportRevenue":0.0564,"descriptor":"veryLow","spikeStatus":"none","period":"shoulder","renewables":56.616070031022026},{"nemTime":"2026-01-31T08:25:00+10:00","hour":8,"minute":25,"importKwh":0.005,"exportKwh":0.005,"importPrice":15.04847,"exportPrice":5.71303,"importCost":0.0752,"exportRevenue":0.0286,"descriptor":"veryLow","spikeStatus":"none","period":"shoulder","renewables":56.97610254234704},{"nemTime":"2026-01-31T08:30:00+10:00","hour":8,"minute":30,"importKwh":0.009,"exportKwh":0.006,"importPrice":13.29476,"exportPrice":4.11875,"importCost":0.1197,"exportRevenue":0.0247,"descriptor":"veryLow","spikeStatus":"none","period":"shoulder","renewables":57.15590099962744},{"nemTime":"2026-01-31T08:35:00+10:00","hour":8,"minute":35,"importKwh":0.009,"exportKwh":0.008,"importPrice":12.82971,"exportPrice":3.69598,"importCost":0.1155,"exportRevenue":0.0296,"descriptor":"extremelyLow","spikeStatus":"none","period":"shoulder","renewables":61.12640709576876},{"nemTime":"2026-01-31T08:40:00+10:00","hour":8,"minute":40,"importKwh":0.012,"exportKwh":0.016,"importPrice":14.95961,"exportPrice":5.63225,"importCost":0.1795,"exportRevenue":0.0901,"descriptor":"veryLow","spikeStatus":"none","period":"shoulder","renewables":62.07349833444581},{"nemTime":"2026-01-31T08:45:00+10:00","hour":8,"minute":45,"importKwh":0.012,"exportKwh":0.013,"importPrice":12.82971,"exportPrice":3.69598,"importCost":0.154,"exportRevenue":0.048,"descriptor":"extremelyLow","spikeStatus":"none","period":"shoulder","renewables":61.57836577734847},{"nemTime":"2026-01-31T08:50:00+10:00","hour":8,"minute":50,"importKwh":0.016,"exportKwh":0.012,"importPrice":12.73358,"exportPrice":3.60858,"importCost":0.2037,"exportRevenue":0.0433,"descriptor":"extremelyLow","spikeStatus":"none","period":"shoulder","renewables":63.697047719271474},{"nemTime":"2026-01-31T08:55:00+10:00","hour":8,"minute":55,"importKwh":0.011,"exportKwh":0.014,"importPrice":11.23968,"exportPrice":2.25049,"importCost":0.1236,"exportRevenue":0.0315,"descriptor":"extremelyLow","spikeStatus":"none","period":"shoulder","renewables":64.66218989531774},{"nemTime":"2026-01-31T09:00:00+10:00","hour":9,"minute":0,"importKwh":0.016,"exportKwh":0.016,"importPrice":11.19071,"exportPrice":2.20598,"importCost":0.1791,"exportRevenue":0.0353,"descriptor":"extremelyLow","spikeStatus":"none","period":"shoulder","renewables":64.09422931633642},{"nemTime":"2026-01-31T09:05:00+10:00","hour":9,"minute":5,"importKwh":0.013,"exportKwh":0.011,"importPrice":11.18563,"exportPrice":2.20136,"importCost":0.1454,"exportRevenue":0.0242,"descriptor":"extremelyLow","spikeStatus":"none","period":"shoulder","renewables":66.11873575339877},{"nemTime":"2026-01-31T09:10:00+10:00","hour":9,"minute":10,"importKwh":0.009,"exportKwh":0.011,"importPrice":12.61213,"exportPrice":3.49818,"importCost":0.1135,"exportRevenue":0.0385,"descriptor":"extremelyLow","spikeStatus":"none","period":"shoulder","renewables":67.0456708259698},{"nemTime":"2026-01-31T09:15:00+10:00","hour":9,"minute":15,"importKwh":0.031,"exportKwh":0.016,"importPrice":11.12676,"exportPrice":2.14783,"importCost":0.3449,"exportRevenue":0.0344,"descriptor":"extremelyLow","spikeStatus":"none","period":"shoulder","renewables":68.48491802130454},{"nemTime":"2026-01-31T09:20:00+10:00","hour":9,"minute":20,"importKwh":0.012,"exportKwh":0.01,"importPrice":11.12676,"exportPrice":2.14783,"importCost":0.1335,"exportRevenue":0.0215,"descriptor":"extremelyLow","spikeStatus":"none","period":"shoulder","renewables":69.51822696404035},{"nemTime":"2026-01-31T09:25:00+10:00","hour":9,"minute":25,"importKwh":0.018,"exportKwh":0.015,"importPrice":8.76765,"exportPrice":0.00319,"importCost":0.1578,"exportRevenue":0,"descriptor":"extremelyLow","spikeStatus":"none","period":"shoulder","renewables":72.20726226753293},{"nemTime":"2026-01-31T09:30:00+10:00","hour":9,"minute":30,"importKwh":0.007,"exportKwh":0.004,"importPrice":11.12676,"exportPrice":2.14783,"importCost":0.0779,"exportRevenue":0.0086,"descriptor":"extremelyLow","spikeStatus":"none","period":"shoulder","renewables":73.02813790162169},{"nemTime":"2026-01-31T09:35:00+10:00","hour":9,"minute":35,"importKwh":0.009,"exportKwh":0.008,"importPrice":12.56226,"exportPrice":3.45283,"importCost":0.1131,"exportRevenue":0.0276,"descriptor":"extremelyLow","spikeStatus":"none","period":"shoulder","renewables":72.98895810789728},{"nemTime":"2026-01-31T09:40:00+10:00","hour":9,"minute":40,"importKwh":0.005,"exportKwh":0.006,"importPrice":13.48704,"exportPrice":4.29354,"importCost":0.0674,"exportRevenue":0.0258,"descriptor":"veryLow","spikeStatus":"none","period":"shoulder","renewables":71.54820698084735},{"nemTime":"2026-01-31T09:45:00+10:00","hour":9,"minute":45,"importKwh":0.041,"exportKwh":0.023,"importPrice":11.27829,"exportPrice":2.28559,"importCost":0.4624,"exportRevenue":0.0526,"descriptor":"extremelyLow","spikeStatus":"none","period":"shoulder","renewables":71.76095578059575},{"nemTime":"2026-01-31T09:50:00+10:00","hour":9,"minute":50,"importKwh":0.016,"exportKwh":0.013,"importPrice":8.77116,"exportPrice":0.00638,"importCost":0.1403,"exportRevenue":0.0001,"descriptor":"extremelyLow","spikeStatus":"none","period":"shoulder","renewables":73.1738801390103},{"nemTime":"2026-01-31T09:55:00+10:00","hour":9,"minute":55,"importKwh":0.02,"exportKwh":0.012,"importPrice":10.40043,"exportPrice":1.48753,"importCost":0.208,"exportRevenue":0.0179,"descriptor":"extremelyLow","spikeStatus":"none","period":"shoulder","renewables":73.78869017317756},{"nemTime":"2026-01-31T10:00:00+10:00","hour":10,"minute":0,"importKwh":0.014,"exportKwh":0.017,"importPrice":12.73376,"exportPrice":3.60875,"importCost":0.1783,"exportRevenue":0.0613,"descriptor":"extremelyLow","spikeStatus":"none","period":"shoulder","renewables":70.18046298744622},{"nemTime":"2026-01-31T10:05:00+10:00","hour":10,"minute":5,"importKwh":0.012,"exportKwh":0.02,"importPrice":12.73468,"exportPrice":3.60958,"importCost":0.1528,"exportRevenue":0.0722,"descriptor":"extremelyLow","spikeStatus":"none","period":"shoulder","renewables":69.8619731149178},{"nemTime":"2026-01-31T10:10:00+10:00","hour":10,"minute":10,"importKwh":0.018,"exportKwh":0.012,"importPrice":12.68241,"exportPrice":3.56206,"importCost":0.2283,"exportRevenue":0.0427,"descriptor":"extremelyLow","spikeStatus":"none","period":"shoulder","renewables":69.83294361240822},{"nemTime":"2026-01-31T10:15:00+10:00","hour":10,"minute":15,"importKwh":0.009,"exportKwh":0.009,"importPrice":12.78718,"exportPrice":3.65731,"importCost":0.1151,"exportRevenue":0.0329,"descriptor":"extremelyLow","spikeStatus":"none","period":"shoulder","renewables":69.24431355891035},{"nemTime":"2026-01-31T10:20:00+10:00","hour":10,"minute":20,"importKwh":0.013,"exportKwh":0.008,"importPrice":12.82971,"exportPrice":3.69598,"importCost":0.1668,"exportRevenue":0.0296,"descriptor":"extremelyLow","spikeStatus":"none","period":"shoulder","renewables":69.0404699789054},{"nemTime":"2026-01-31T10:25:00+10:00","hour":10,"minute":25,"importKwh":0.008,"exportKwh":0.005,"importPrice":12.91932,"exportPrice":3.77743,"importCost":0.1034,"exportRevenue":0.0189,"descriptor":"extremelyLow","spikeStatus":"none","period":"shoulder","renewables":68.31002640964844},{"nemTime":"2026-01-31T10:30:00+10:00","hour":10,"minute":30,"importKwh":0.016,"exportKwh":0.013,"importPrice":12.84365,"exportPrice":3.70865,"importCost":0.2055,"exportRevenue":0.0482,"descriptor":"extremelyLow","spikeStatus":"none","period":"shoulder","renewables":68.70100830650391},{"nemTime":"2026-01-31T10:35:00+10:00","hour":10,"minute":35,"importKwh":0.015,"exportKwh":0.013,"importPrice":12.89476,"exportPrice":3.7551,"importCost":0.1934,"exportRevenue":0.0488,"descriptor":"extremelyLow","spikeStatus":"none","period":"shoulder","renewables":68.37050335364411},{"nemTime":"2026-01-31T10:40:00+10:00","hour":10,"minute":40,"importKwh":0.023,"exportKwh":0.021,"importPrice":12.84034,"exportPrice":3.70563,"importCost":0.2953,"exportRevenue":0.0778,"descriptor":"extremelyLow","spikeStatus":"none","period":"shoulder","renewables":69.01828033438751},{"nemTime":"2026-01-31T10:45:00+10:00","hour":10,"minute":45,"importKwh":0.27,"exportKwh":0.004,"importPrice":11.51157,"exportPrice":2.49766,"importCost":3.1081,"exportRevenue":0.01,"descriptor":"extremelyLow","spikeStatus":"none","period":"shoulder","renewables":69.66915102216188},{"nemTime":"2026-01-31T10:50:00+10:00","hour":10,"minute":50,"importKwh":0.557,"exportKwh":0,"importPrice":12.78753,"exportPrice":3.65763,"importCost":7.1227,"exportRevenue":0,"descriptor":"extremelyLow","spikeStatus":"none","period":"shoulder","renewables":70.71076790847167},{"nemTime":"2026-01-31T10:55:00+10:00","hour":10,"minute":55,"importKwh":0.373,"exportKwh":0,"importPrice":12.94317,"exportPrice":3.79911,"importCost":4.8278,"exportRevenue":0,"descriptor":"extremelyLow","spikeStatus":"none","period":"shoulder","renewables":70.14457474339348},{"nemTime":"2026-01-31T11:00:00+10:00","hour":11,"minute":0,"importKwh":0.377,"exportKwh":0,"importPrice":13.10109,"exportPrice":3.94268,"importCost":4.9391,"exportRevenue":0,"descriptor":"extremelyLow","spikeStatus":"none","period":"shoulder","renewables":68.62704061632611},{"nemTime":"2026-01-31T11:05:00+10:00","hour":11,"minute":5,"importKwh":0.311,"exportKwh":0,"importPrice":8.11309,"exportPrice":3.80014,"importCost":2.5232,"exportRevenue":0,"descriptor":"extremelyLow","spikeStatus":"none","period":"offPeak","renewables":68.32712571036974},{"nemTime":"2026-01-31T11:10:00+10:00","hour":11,"minute":10,"importKwh":0.299,"exportKwh":0,"importPrice":8.11197,"exportPrice":3.79911,"importCost":2.4255,"exportRevenue":0,"descriptor":"extremelyLow","spikeStatus":"none","period":"offPeak","renewables":70.28703390008141},{"nemTime":"2026-01-31T11:15:00+10:00","hour":11,"minute":15,"importKwh":0.316,"exportKwh":0,"importPrice":8.19275,"exportPrice":3.87256,"importCost":2.5889,"exportRevenue":0,"descriptor":"extremelyLow","spikeStatus":"none","period":"offPeak","renewables":70.95204211840841},{"nemTime":"2026-01-31T11:20:00+10:00","hour":11,"minute":20,"importKwh":0.238,"exportKwh":0,"importPrice":8.42425,"exportPrice":4.08301,"importCost":2.005,"exportRevenue":0,"descriptor":"extremelyLow","spikeStatus":"none","period":"offPeak","renewables":69.94252925502671},{"nemTime":"2026-01-31T11:25:00+10:00","hour":11,"minute":25,"importKwh":0.228,"exportKwh":0,"importPrice":8.36343,"exportPrice":4.02772,"importCost":1.9069,"exportRevenue":0,"descriptor":"extremelyLow","spikeStatus":"none","period":"offPeak","renewables":71.9949727660562},{"nemTime":"2026-01-31T11:30:00+10:00","hour":11,"minute":30,"importKwh":0.175,"exportKwh":0,"importPrice":8.93611,"exportPrice":4.54833,"importCost":1.5638,"exportRevenue":0,"descriptor":"extremelyLow","spikeStatus":"none","period":"offPeak","renewables":70.48955927552637},{"nemTime":"2026-01-31T11:35:00+10:00","hour":11,"minute":35,"importKwh":0.272,"exportKwh":0,"importPrice":8.74466,"exportPrice":4.37429,"importCost":2.3785,"exportRevenue":0,"descriptor":"extremelyLow","spikeStatus":"none","period":"offPeak","renewables":70.8332554959464},{"nemTime":"2026-01-31T11:40:00+10:00","hour":11,"minute":40,"importKwh":0.4,"exportKwh":0,"importPrice":10.36464,"exportPrice":5.847,"importCost":4.1459,"exportRevenue":0,"descriptor":"extremelyLow","spikeStatus":"none","period":"offPeak","renewables":71.03556883880573},{"nemTime":"2026-01-31T11:45:00+10:00","hour":11,"minute":45,"importKwh":0.555,"exportKwh":0,"importPrice":9.19035,"exportPrice":4.77946,"importCost":5.1006,"exportRevenue":0,"descriptor":"extremelyLow","spikeStatus":"none","period":"offPeak","renewables":74.11521014620087},{"nemTime":"2026-01-31T11:50:00+10:00","hour":11,"minute":50,"importKwh":0.525,"exportKwh":0,"importPrice":8.3646,"exportPrice":4.02878,"importCost":4.3914,"exportRevenue":0,"descriptor":"extremelyLow","spikeStatus":"none","period":"offPeak","renewables":73.97861793467786},{"nemTime":"2026-01-31T11:55:00+10:00","hour":11,"minute":55,"importKwh":0.563,"exportKwh":0,"importPrice":9.67375,"exportPrice":5.21892,"importCost":5.4463,"exportRevenue":0,"descriptor":"extremelyLow","spikeStatus":"none","period":"offPeak","renewables":70.86714271712626},{"nemTime":"2026-01-31T12:00:00+10:00","hour":12,"minute":0,"importKwh":0.559,"exportKwh":0,"importPrice":8.62546,"exportPrice":4.26593,"importCost":4.8216,"exportRevenue":0,"descriptor":"extremelyLow","spikeStatus":"none","period":"offPeak","renewables":69.99269710594456},{"nemTime":"2026-01-31T12:05:00+10:00","hour":12,"minute":5,"importKwh":0.472,"exportKwh":0,"importPrice":10.36464,"exportPrice":5.847,"importCost":4.8921,"exportRevenue":0,"descriptor":"extremelyLow","spikeStatus":"none","period":"offPeak","renewables":70.82730395521294},{"nemTime":"2026-01-31T12:10:00+10:00","hour":12,"minute":10,"importKwh":0.202,"exportKwh":0.005,"importPrice":8.43866,"exportPrice":4.09611,"importCost":1.7046,"exportRevenue":0.0205,"descriptor":"extremelyLow","spikeStatus":"none","period":"offPeak","renewables":74.00224950324125},{"nemTime":"2026-01-31T12:15:00+10:00","hour":12,"minute":15,"importKwh":0.012,"exportKwh":0.006,"importPrice":9.09082,"exportPrice":4.68898,"importCost":0.1091,"exportRevenue":0.0281,"descriptor":"extremelyLow","spikeStatus":"none","period":"offPeak","renewables":74.60394014649674},{"nemTime":"2026-01-31T12:20:00+10:00","hour":12,"minute":20,"importKwh":0.173,"exportKwh":0.007,"importPrice":9.90264,"exportPrice":5.427,"importCost":1.7132,"exportRevenue":0.038,"descriptor":"extremelyLow","spikeStatus":"none","period":"offPeak","renewables":74.63875752426215},{"nemTime":"2026-01-31T12:25:00+10:00","hour":12,"minute":25,"importKwh":0.236,"exportKwh":0.038,"importPrice":9.15244,"exportPrice":4.745,"importCost":2.16,"exportRevenue":0.1803,"descriptor":"extremelyLow","spikeStatus":"none","period":"offPeak","renewables":74.81322872049229},{"nemTime":"2026-01-31T12:30:00+10:00","hour":12,"minute":30,"importKwh":0.147,"exportKwh":0.023,"importPrice":9.90264,"exportPrice":5.427,"importCost":1.4557,"exportRevenue":0.1248,"descriptor":"extremelyLow","spikeStatus":"none","period":"offPeak","renewables":71.47431189286321},{"nemTime":"2026-01-31T12:35:00+10:00","hour":12,"minute":35,"importKwh":0.128,"exportKwh":0.01,"importPrice":9.19035,"exportPrice":4.77946,"importCost":1.1764,"exportRevenue":0.0478,"descriptor":"extremelyLow","spikeStatus":"none","period":"offPeak","renewables":73.56028721622474},{"nemTime":"2026-01-31T12:40:00+10:00","hour":12,"minute":40,"importKwh":0.009,"exportKwh":0.072,"importPrice":10.32074,"exportPrice":5.80709,"importCost":0.0929,"exportRevenue":0.4181,"descriptor":"extremelyLow","spikeStatus":"none","period":"offPeak","renewables":72.98674351168556},{"nemTime":"2026-01-31T12:45:00+10:00","hour":12,"minute":45,"importKwh":0.019,"exportKwh":0.064,"importPrice":8.11197,"exportPrice":3.79911,"importCost":0.1541,"exportRevenue":0.2431,"descriptor":"extremelyLow","spikeStatus":"none","period":"offPeak","renewables":74.71678863485684},{"nemTime":"2026-01-31T12:50:00+10:00","hour":12,"minute":50,"importKwh":0.019,"exportKwh":0.014,"importPrice":9.90264,"exportPrice":5.427,"importCost":0.1882,"exportRevenue":0.076,"descriptor":"extremelyLow","spikeStatus":"none","period":"offPeak","renewables":73.57563882955785},{"nemTime":"2026-01-31T12:55:00+10:00","hour":12,"minute":55,"importKwh":0.018,"exportKwh":0.01,"importPrice":5.56923,"exportPrice":1.48753,"importCost":0.1002,"exportRevenue":0.0149,"descriptor":"extremelyLow","spikeStatus":"none","period":"offPeak","renewables":75.74749364147493},{"nemTime":"2026-01-31T13:00:00+10:00","hour":13,"minute":0,"importKwh":0.01,"exportKwh":0.066,"importPrice":8.36343,"exportPrice":4.02772,"importCost":0.0836,"exportRevenue":0.2658,"descriptor":"extremelyLow","spikeStatus":"none","period":"offPeak","renewables":76.18540061791879},{"nemTime":"2026-01-31T13:05:00+10:00","hour":13,"minute":5,"importKwh":0.017,"exportKwh":0.044,"importPrice":8.11197,"exportPrice":3.79911,"importCost":0.1379,"exportRevenue":0.1672,"descriptor":"extremelyLow","spikeStatus":"none","period":"offPeak","renewables":74.95781970185355},{"nemTime":"2026-01-31T13:10:00+10:00","hour":13,"minute":10,"importKwh":0.024,"exportKwh":0.026,"importPrice":8.3646,"exportPrice":4.02878,"importCost":0.2008,"exportRevenue":0.1047,"descriptor":"extremelyLow","spikeStatus":"none","period":"offPeak","renewables":74.3974883134163},{"nemTime":"2026-01-31T13:15:00+10:00","hour":13,"minute":15,"importKwh":0.033,"exportKwh":0.038,"importPrice":9.90264,"exportPrice":5.427,"importCost":0.3268,"exportRevenue":0.2062,"descriptor":"extremelyLow","spikeStatus":"none","period":"offPeak","renewables":76.03302129506247},{"nemTime":"2026-01-31T13:20:00+10:00","hour":13,"minute":20,"importKwh":0.004,"exportKwh":0.03,"importPrice":10.36464,"exportPrice":5.847,"importCost":0.0415,"exportRevenue":0.1754,"descriptor":"extremelyLow","spikeStatus":"none","period":"offPeak","renewables":75.65653777289462},{"nemTime":"2026-01-31T13:25:00+10:00","hour":13,"minute":25,"importKwh":0.001,"exportKwh":0.006,"importPrice":10.36464,"exportPrice":5.847,"importCost":0.0104,"exportRevenue":0.0351,"descriptor":"extremelyLow","spikeStatus":"none","period":"offPeak","renewables":75.12731854617707},{"nemTime":"2026-01-31T13:30:00+10:00","hour":13,"minute":30,"importKwh":0.003,"exportKwh":0.002,"importPrice":10.19461,"exportPrice":5.69243,"importCost":0.0306,"exportRevenue":0.0114,"descriptor":"extremelyLow","spikeStatus":"none","period":"offPeak","renewables":74.10830668086919},{"nemTime":"2026-01-31T13:35:00+10:00","hour":13,"minute":35,"importKwh":0.008,"exportKwh":0.007,"importPrice":9.781,"exportPrice":5.31642,"importCost":0.0782,"exportRevenue":0.0372,"descriptor":"extremelyLow","spikeStatus":"none","period":"offPeak","renewables":75.10626191289437},{"nemTime":"2026-01-31T13:40:00+10:00","hour":13,"minute":40,"importKwh":0.009,"exportKwh":0.002,"importPrice":8.15875,"exportPrice":3.84165,"importCost":0.0734,"exportRevenue":0.0077,"descriptor":"extremelyLow","spikeStatus":"none","period":"offPeak","renewables":75.53524751253089},{"nemTime":"2026-01-31T13:45:00+10:00","hour":13,"minute":45,"importKwh":0.001,"exportKwh":0.121,"importPrice":9.781,"exportPrice":5.31642,"importCost":0.0098,"exportRevenue":0.6433,"descriptor":"extremelyLow","spikeStatus":"none","period":"offPeak","renewables":74.26371716490617},{"nemTime":"2026-01-31T13:50:00+10:00","hour":13,"minute":50,"importKwh":0,"exportKwh":0.318,"importPrice":9.781,"exportPrice":5.31642,"importCost":0,"exportRevenue":1.6906,"descriptor":"extremelyLow","spikeStatus":"none","period":"offPeak","renewables":72.83616666795382},{"nemTime":"2026-01-31T13:55:00+10:00","hour":13,"minute":55,"importKwh":0,"exportKwh":0.463,"importPrice":9.90264,"exportPrice":5.427,"importCost":0,"exportRevenue":2.5127,"descriptor":"extremelyLow","spikeStatus":"none","period":"offPeak","renewables":72.8729272190251},{"nemTime":"2026-01-31T14:00:00+10:00","hour":14,"minute":0,"importKwh":0,"exportKwh":0.445,"importPrice":9.90264,"exportPrice":5.427,"importCost":0,"exportRevenue":2.415,"descriptor":"extremelyLow","spikeStatus":"none","period":"offPeak","renewables":71.83953147873994},{"nemTime":"2026-01-31T14:05:00+10:00","hour":14,"minute":5,"importKwh":0,"exportKwh":0.365,"importPrice":9.90264,"exportPrice":5.427,"importCost":0,"exportRevenue":1.9809,"descriptor":"extremelyLow","spikeStatus":"none","period":"offPeak","renewables":69.46899932470775},{"nemTime":"2026-01-31T14:10:00+10:00","hour":14,"minute":10,"importKwh":0,"exportKwh":0.255,"importPrice":10.16653,"exportPrice":5.6669,"importCost":0,"exportRevenue":1.4451,"descriptor":"extremelyLow","spikeStatus":"none","period":"offPeak","renewables":69.40290914600418},{"nemTime":"2026-01-31T14:15:00+10:00","hour":14,"minute":15,"importKwh":0,"exportKwh":0.271,"importPrice":10.16823,"exportPrice":5.66845,"importCost":0,"exportRevenue":1.5361,"descriptor":"extremelyLow","spikeStatus":"none","period":"offPeak","renewables":70.03242143143976},{"nemTime":"2026-01-31T14:20:00+10:00","hour":14,"minute":20,"importKwh":0,"exportKwh":0.26,"importPrice":10.25506,"exportPrice":5.74738,"importCost":0,"exportRevenue":1.4943,"descriptor":"extremelyLow","spikeStatus":"none","period":"offPeak","renewables":69.62418159129537},{"nemTime":"2026-01-31T14:25:00+10:00","hour":14,"minute":25,"importKwh":0,"exportKwh":0.247,"importPrice":9.90264,"exportPrice":5.427,"importCost":0,"exportRevenue":1.3405,"descriptor":"extremelyLow","spikeStatus":"none","period":"offPeak","renewables":68.33061389519877},{"nemTime":"2026-01-31T14:30:00+10:00","hour":14,"minute":30,"importKwh":0,"exportKwh":0.295,"importPrice":10.36464,"exportPrice":5.847,"importCost":0,"exportRevenue":1.7249,"descriptor":"extremelyLow","spikeStatus":"none","period":"offPeak","renewables":67.624832666985},{"nemTime":"2026-01-31T14:35:00+10:00","hour":14,"minute":35,"importKwh":0,"exportKwh":0.404,"importPrice":8.27528,"exportPrice":3.94758,"importCost":0,"exportRevenue":1.5948,"descriptor":"extremelyLow","spikeStatus":"none","period":"offPeak","renewables":67.48209458895964},{"nemTime":"2026-01-31T14:40:00+10:00","hour":14,"minute":40,"importKwh":0,"exportKwh":0.389,"importPrice":10.07529,"exportPrice":5.58395,"importCost":0,"exportRevenue":2.1722,"descriptor":"extremelyLow","spikeStatus":"none","period":"offPeak","renewables":67.57486443572994},{"nemTime":"2026-01-31T14:45:00+10:00","hour":14,"minute":45,"importKwh":0,"exportKwh":0.396,"importPrice":9.19035,"exportPrice":4.77946,"importCost":0,"exportRevenue":1.8927,"descriptor":"extremelyLow","spikeStatus":"none","period":"offPeak","renewables":67.33275320806848},{"nemTime":"2026-01-31T14:50:00+10:00","hour":14,"minute":50,"importKwh":0,"exportKwh":0.393,"importPrice":9.90264,"exportPrice":5.427,"importCost":0,"exportRevenue":2.1328,"descriptor":"extremelyLow","spikeStatus":"none","period":"offPeak","renewables":65.68475258819439},{"nemTime":"2026-01-31T14:55:00+10:00","hour":14,"minute":55,"importKwh":0,"exportKwh":0.439,"importPrice":9.83948,"exportPrice":5.36959,"importCost":0,"exportRevenue":2.3572,"descriptor":"extremelyLow","spikeStatus":"none","period":"offPeak","renewables":63.69931104768541},{"nemTime":"2026-01-31T15:00:00+10:00","hour":15,"minute":0,"importKwh":0,"exportKwh":0.42,"importPrice":10.04024,"exportPrice":5.55209,"importCost":0,"exportRevenue":2.3319,"descriptor":"extremelyLow","spikeStatus":"none","period":"offPeak","renewables":63.81736073530669},{"nemTime":"2026-01-31T15:05:00+10:00","hour":15,"minute":5,"importKwh":0,"exportKwh":0.41,"importPrice":10.36464,"exportPrice":5.847,"importCost":0,"exportRevenue":2.3973,"descriptor":"extremelyLow","spikeStatus":"none","period":"offPeak","renewables":61.005435151923294},{"nemTime":"2026-01-31T15:10:00+10:00","hour":15,"minute":10,"importKwh":0,"exportKwh":0.379,"importPrice":10.18783,"exportPrice":5.68626,"importCost":0,"exportRevenue":2.1551,"descriptor":"extremelyLow","spikeStatus":"none","period":"offPeak","renewables":60.67260491190666},{"nemTime":"2026-01-31T15:15:00+10:00","hour":15,"minute":15,"importKwh":0,"exportKwh":0.365,"importPrice":10.19505,"exportPrice":5.69282,"importCost":0,"exportRevenue":2.0779,"descriptor":"extremelyLow","spikeStatus":"none","period":"offPeak","renewables":60.445235395372585},{"nemTime":"2026-01-31T15:20:00+10:00","hour":15,"minute":20,"importKwh":0,"exportKwh":0.358,"importPrice":10.21285,"exportPrice":5.70901,"importCost":0,"exportRevenue":2.0438,"descriptor":"extremelyLow","spikeStatus":"none","period":"offPeak","renewables":59.60202366176264},{"nemTime":"2026-01-31T15:25:00+10:00","hour":15,"minute":25,"importKwh":0,"exportKwh":0.339,"importPrice":10.36464,"exportPrice":5.847,"importCost":0,"exportRevenue":1.9821,"descriptor":"extremelyLow","spikeStatus":"none","period":"offPeak","renewables":59.900963093549876},{"nemTime":"2026-01-31T15:30:00+10:00","hour":15,"minute":30,"importKwh":0,"exportKwh":0.313,"importPrice":11.15295,"exportPrice":6.56364,"importCost":0,"exportRevenue":2.0544,"descriptor":"extremelyLow","spikeStatus":"none","period":"offPeak","renewables":58.20407132541684},{"nemTime":"2026-01-31T15:35:00+10:00","hour":15,"minute":35,"importKwh":0,"exportKwh":0.237,"importPrice":10.55337,"exportPrice":6.01858,"importCost":0,"exportRevenue":1.4264,"descriptor":"extremelyLow","spikeStatus":"none","period":"offPeak","renewables":54.8298794660798},{"nemTime":"2026-01-31T15:40:00+10:00","hour":15,"minute":40,"importKwh":0,"exportKwh":0.197,"importPrice":10.53513,"exportPrice":6.00199,"importCost":0,"exportRevenue":1.1824,"descriptor":"extremelyLow","spikeStatus":"none","period":"offPeak","renewables":54.41603048170972},{"nemTime":"2026-01-31T15:45:00+10:00","hour":15,"minute":45,"importKwh":0,"exportKwh":0.17,"importPrice":10.63041,"exportPrice":6.08861,"importCost":0,"exportRevenue":1.0351,"descriptor":"extremelyLow","spikeStatus":"none","period":"offPeak","renewables":53.22821217177579},{"nemTime":"2026-01-31T15:50:00+10:00","hour":15,"minute":50,"importKwh":0.001,"exportKwh":0.16,"importPrice":12.93543,"exportPrice":8.18408,"importCost":0.0129,"exportRevenue":1.3095,"descriptor":"extremelyLow","spikeStatus":"none","period":"offPeak","renewables":51.934094631383196},{"nemTime":"2026-01-31T15:55:00+10:00","hour":15,"minute":55,"importKwh":0,"exportKwh":0.196,"importPrice":18.17064,"exportPrice":12.94336,"importCost":0,"exportRevenue":2.5369,"descriptor":"veryLow","spikeStatus":"none","period":"offPeak","renewables":51.741301898638966},{"nemTime":"2026-01-31T16:00:00+10:00","hour":16,"minute":0,"importKwh":0,"exportKwh":0.124,"importPrice":17.96829,"exportPrice":12.75941,"importCost":0,"exportRevenue":1.5822,"descriptor":"veryLow","spikeStatus":"none","period":"offPeak","renewables":50.893643588170775},{"nemTime":"2026-01-31T16:05:00+10:00","hour":16,"minute":5,"importKwh":0.004,"exportKwh":0.11,"importPrice":33.1022,"exportPrice":7.62651,"importCost":0.1324,"exportRevenue":0.8389,"descriptor":"low","spikeStatus":"none","period":"peak","renewables":47.15348167569006},{"nemTime":"2026-01-31T16:10:00+10:00","hour":16,"minute":10,"importKwh":0.007,"exportKwh":0,"importPrice":33.12196,"exportPrice":7.64447,"importCost":0.2319,"exportRevenue":0,"descriptor":"low","spikeStatus":"none","period":"peak","renewables":46.23442074366228},{"nemTime":"2026-01-31T16:15:00+10:00","hour":16,"minute":15,"importKwh":0.007,"exportKwh":0,"importPrice":33.24537,"exportPrice":7.75666,"importCost":0.2327,"exportRevenue":0,"descriptor":"low","spikeStatus":"none","period":"peak","renewables":46.9925757354253},{"nemTime":"2026-01-31T16:20:00+10:00","hour":16,"minute":20,"importKwh":0.02,"exportKwh":0,"importPrice":34.25471,"exportPrice":8.67424,"importCost":0.6851,"exportRevenue":0,"descriptor":"low","spikeStatus":"none","period":"peak","renewables":44.038933654720566},{"nemTime":"2026-01-31T16:25:00+10:00","hour":16,"minute":25,"importKwh":0.065,"exportKwh":0,"importPrice":34.30268,"exportPrice":8.71786,"importCost":2.2297,"exportRevenue":0,"descriptor":"low","spikeStatus":"none","period":"peak","renewables":43.73172677150098},{"nemTime":"2026-01-31T16:30:00+10:00","hour":16,"minute":30,"importKwh":0.139,"exportKwh":0,"importPrice":33.23835,"exportPrice":7.75028,"importCost":4.6201,"exportRevenue":0,"descriptor":"low","spikeStatus":"none","period":"peak","renewables":42.92907222076241},{"nemTime":"2026-01-31T16:35:00+10:00","hour":16,"minute":35,"importKwh":0.096,"exportKwh":0,"importPrice":32.29567,"exportPrice":6.8933,"importCost":3.1004,"exportRevenue":0,"descriptor":"low","spikeStatus":"none","period":"peak","renewables":37.42429217709387},{"nemTime":"2026-01-31T16:40:00+10:00","hour":16,"minute":40,"importKwh":0.087,"exportKwh":0,"importPrice":34.60497,"exportPrice":8.99266,"importCost":3.0106,"exportRevenue":0,"descriptor":"low","spikeStatus":"none","period":"peak","renewables":36.616958578143326},{"nemTime":"2026-01-31T16:45:00+10:00","hour":16,"minute":45,"importKwh":0.114,"exportKwh":0,"importPrice":34.56558,"exportPrice":8.95686,"importCost":3.9405,"exportRevenue":0,"descriptor":"low","spikeStatus":"none","period":"peak","renewables":36.99087441874466},{"nemTime":"2026-01-31T16:50:00+10:00","hour":16,"minute":50,"importKwh":0.138,"exportKwh":0,"importPrice":35.35067,"exportPrice":9.67057,"importCost":4.8784,"exportRevenue":0,"descriptor":"low","spikeStatus":"none","period":"peak","renewables":36.117072785446624},{"nemTime":"2026-01-31T16:55:00+10:00","hour":16,"minute":55,"importKwh":0.319,"exportKwh":0,"importPrice":34.14714,"exportPrice":8.57645,"importCost":10.8929,"exportRevenue":0,"descriptor":"low","spikeStatus":"none","period":"peak","renewables":36.58586147017574},{"nemTime":"2026-01-31T17:00:00+10:00","hour":17,"minute":0,"importKwh":0.365,"exportKwh":0,"importPrice":34.83914,"exportPrice":9.20555,"importCost":12.7163,"exportRevenue":0,"descriptor":"low","spikeStatus":"none","period":"peak","renewables":36.01189415908756},{"nemTime":"2026-01-31T17:05:00+10:00","hour":17,"minute":5,"importKwh":0.161,"exportKwh":0.002,"importPrice":32.1471,"exportPrice":6.75824,"importCost":5.1757,"exportRevenue":0.0135,"descriptor":"low","spikeStatus":"none","period":"peak","renewables":29.74838772554528},{"nemTime":"2026-01-31T17:10:00+10:00","hour":17,"minute":10,"importKwh":0.489,"exportKwh":0.001,"importPrice":32.29565,"exportPrice":6.89328,"importCost":15.7926,"exportRevenue":0.0069,"descriptor":"low","spikeStatus":"none","period":"peak","renewables":29.131041554035157},{"nemTime":"2026-01-31T17:15:00+10:00","hour":17,"minute":15,"importKwh":0.64,"exportKwh":0,"importPrice":33.24537,"exportPrice":7.75666,"importCost":21.277,"exportRevenue":0,"descriptor":"low","spikeStatus":"none","period":"peak","renewables":29.05491730169205},{"nemTime":"2026-01-31T17:20:00+10:00","hour":17,"minute":20,"importKwh":0.335,"exportKwh":0,"importPrice":34.06643,"exportPrice":8.50308,"importCost":11.4123,"exportRevenue":0,"descriptor":"low","spikeStatus":"none","period":"peak","renewables":28.343898812251656},{"nemTime":"2026-01-31T17:25:00+10:00","hour":17,"minute":25,"importKwh":0.679,"exportKwh":0,"importPrice":36.14367,"exportPrice":10.39148,"importCost":24.5415,"exportRevenue":0,"descriptor":"low","spikeStatus":"none","period":"peak","renewables":26.786413024128947},{"nemTime":"2026-01-31T17:30:00+10:00","hour":17,"minute":30,"importKwh":0.291,"exportKwh":0,"importPrice":37.42248,"exportPrice":11.55403,"importCost":10.8899,"exportRevenue":0,"descriptor":"low","spikeStatus":"none","period":"peak","renewables":24.924204955856073},{"nemTime":"2026-01-31T17:35:00+10:00","hour":17,"minute":35,"importKwh":0.664,"exportKwh":0,"importPrice":36.14367,"exportPrice":10.39148,"importCost":23.9994,"exportRevenue":0,"descriptor":"low","spikeStatus":"none","period":"peak","renewables":19.272952663349947},{"nemTime":"2026-01-31T17:40:00+10:00","hour":17,"minute":40,"importKwh":0.097,"exportKwh":0,"importPrice":38.71681,"exportPrice":12.7307,"importCost":3.7555,"exportRevenue":0,"descriptor":"low","spikeStatus":"none","period":"peak","renewables":17.833710010911048},{"nemTime":"2026-01-31T17:45:00+10:00","hour":17,"minute":45,"importKwh":0.114,"exportKwh":0,"importPrice":36.87701,"exportPrice":11.05816,"importCost":4.204,"exportRevenue":0,"descriptor":"low","spikeStatus":"none","period":"peak","renewables":17.85861253941143},{"nemTime":"2026-01-31T17:50:00+10:00","hour":17,"minute":50,"importKwh":0.047,"exportKwh":0.009,"importPrice":37.01973,"exportPrice":11.1879,"importCost":1.7399,"exportRevenue":0.1007,"descriptor":"low","spikeStatus":"none","period":"peak","renewables":16.30583956255687},{"nemTime":"2026-01-31T17:55:00+10:00","hour":17,"minute":55,"importKwh":0.006,"exportKwh":0.001,"importPrice":38.74488,"exportPrice":12.75622,"importCost":0.2325,"exportRevenue":0.0128,"descriptor":"low","spikeStatus":"none","period":"peak","renewables":15.385000435936364},{"nemTime":"2026-01-31T18:00:00+10:00","hour":18,"minute":0,"importKwh":0.005,"exportKwh":0.001,"importPrice":38.74488,"exportPrice":12.75622,"importCost":0.1937,"exportRevenue":0.0128,"descriptor":"low","spikeStatus":"none","period":"peak","renewables":14.300213390709757},{"nemTime":"2026-01-31T18:05:00+10:00","hour":18,"minute":5,"importKwh":0.007,"exportKwh":0.001,"importPrice":38.74488,"exportPrice":12.75622,"importCost":0.2712,"exportRevenue":0.0128,"descriptor":"low","spikeStatus":"none","period":"peak","renewables":8.758937836447812},{"nemTime":"2026-01-31T18:10:00+10:00","hour":18,"minute":10,"importKwh":0.007,"exportKwh":0.002,"importPrice":38.74488,"exportPrice":12.75622,"importCost":0.2712,"exportRevenue":0.0255,"descriptor":"low","spikeStatus":"none","period":"peak","renewables":7.633699390258959},{"nemTime":"2026-01-31T18:15:00+10:00","hour":18,"minute":15,"importKwh":0.006,"exportKwh":0,"importPrice":38.74722,"exportPrice":12.75835,"importCost":0.2325,"exportRevenue":0,"descriptor":"low","spikeStatus":"none","period":"peak","renewables":6.5151205434492026},{"nemTime":"2026-01-31T18:20:00+10:00","hour":18,"minute":20,"importKwh":0.008,"exportKwh":0.004,"importPrice":38.74722,"exportPrice":12.75835,"importCost":0.31,"exportRevenue":0.051,"descriptor":"low","spikeStatus":"none","period":"peak","renewables":5.510759160862613},{"nemTime":"2026-01-31T18:25:00+10:00","hour":18,"minute":25,"importKwh":0.007,"exportKwh":0.001,"importPrice":39.3576,"exportPrice":13.31324,"importCost":0.2755,"exportRevenue":0.0133,"descriptor":"low","spikeStatus":"none","period":"peak","renewables":4.6085718256341055},{"nemTime":"2026-01-31T18:30:00+10:00","hour":18,"minute":30,"importKwh":0.006,"exportKwh":0.002,"importPrice":42.04764,"exportPrice":15.75872,"importCost":0.2523,"exportRevenue":0.0315,"descriptor":"neutral","spikeStatus":"none","period":"peak","renewables":4.1093022759689815},{"nemTime":"2026-01-31T18:35:00+10:00","hour":18,"minute":35,"importKwh":0.008,"exportKwh":0.002,"importPrice":40.38585,"exportPrice":14.24801,"importCost":0.3231,"exportRevenue":0.0285,"descriptor":"low","spikeStatus":"none","period":"peak","renewables":1.5558784869354538},{"nemTime":"2026-01-31T18:40:00+10:00","hour":18,"minute":40,"importKwh":0.006,"exportKwh":0.001,"importPrice":39.0291,"exportPrice":13.0146,"importCost":0.2342,"exportRevenue":0.013,"descriptor":"low","spikeStatus":"none","period":"peak","renewables":1.3553679343033842},{"nemTime":"2026-01-31T18:45:00+10:00","hour":18,"minute":45,"importKwh":0.006,"exportKwh":0.001,"importPrice":41.2393,"exportPrice":15.02387,"importCost":0.2474,"exportRevenue":0.015,"descriptor":"neutral","spikeStatus":"none","period":"peak","renewables":1.3730867558296445},{"nemTime":"2026-01-31T18:50:00+10:00","hour":18,"minute":50,"importKwh":0.007,"exportKwh":0.001,"importPrice":40.31219,"exportPrice":14.18104,"importCost":0.2822,"exportRevenue":0.0142,"descriptor":"low","spikeStatus":"none","period":"peak","renewables":1.3640508473508723},{"nemTime":"2026-01-31T18:55:00+10:00","hour":18,"minute":55,"importKwh":0.006,"exportKwh":0.002,"importPrice":39.0291,"exportPrice":13.0146,"importCost":0.2342,"exportRevenue":0.026,"descriptor":"low","spikeStatus":"none","period":"peak","renewables":1.3414461644975773},{"nemTime":"2026-01-31T19:00:00+10:00","hour":19,"minute":0,"importKwh":0.006,"exportKwh":0.001,"importPrice":41.43175,"exportPrice":15.19883,"importCost":0.2486,"exportRevenue":0.0152,"descriptor":"neutral","spikeStatus":"none","period":"peak","renewables":1.3455879033342812},{"nemTime":"2026-01-31T19:05:00+10:00","hour":19,"minute":5,"importKwh":0.006,"exportKwh":0.002,"importPrice":39.46796,"exportPrice":13.41356,"importCost":0.2368,"exportRevenue":0.0268,"descriptor":"low","spikeStatus":"none","period":"peak","renewables":1.2517529217314503},{"nemTime":"2026-01-31T19:10:00+10:00","hour":19,"minute":10,"importKwh":0.005,"exportKwh":0.001,"importPrice":39.0291,"exportPrice":13.0146,"importCost":0.1951,"exportRevenue":0.013,"descriptor":"low","spikeStatus":"none","period":"peak","renewables":1.4978672330938352},{"nemTime":"2026-01-31T19:15:00+10:00","hour":19,"minute":15,"importKwh":0.007,"exportKwh":0,"importPrice":38.74722,"exportPrice":12.75835,"importCost":0.2712,"exportRevenue":0,"descriptor":"low","spikeStatus":"none","period":"peak","renewables":1.7963531921528604},{"nemTime":"2026-01-31T19:20:00+10:00","hour":19,"minute":20,"importKwh":0.006,"exportKwh":0.001,"importPrice":40.38585,"exportPrice":14.24801,"importCost":0.2423,"exportRevenue":0.0142,"descriptor":"low","spikeStatus":"none","period":"peak","renewables":2.1099372126656397},{"nemTime":"2026-01-31T19:25:00+10:00","hour":19,"minute":25,"importKwh":0.008,"exportKwh":0.002,"importPrice":38.74722,"exportPrice":12.75835,"importCost":0.31,"exportRevenue":0.0255,"descriptor":"low","spikeStatus":"none","period":"peak","renewables":2.564534675832412},{"nemTime":"2026-01-31T19:30:00+10:00","hour":19,"minute":30,"importKwh":0.095,"exportKwh":0,"importPrice":38.74488,"exportPrice":12.75622,"importCost":3.6808,"exportRevenue":0,"descriptor":"low","spikeStatus":"none","period":"peak","renewables":2.8433057737307905},{"nemTime":"2026-01-31T19:35:00+10:00","hour":19,"minute":35,"importKwh":0.101,"exportKwh":0,"importPrice":38.74839,"exportPrice":12.75941,"importCost":3.9136,"exportRevenue":0,"descriptor":"low","spikeStatus":"none","period":"peak","renewables":3.233682468492875},{"nemTime":"2026-01-31T19:40:00+10:00","hour":19,"minute":40,"importKwh":0.1,"exportKwh":0,"importPrice":38.20373,"exportPrice":12.26426,"importCost":3.8204,"exportRevenue":0,"descriptor":"low","spikeStatus":"none","period":"peak","renewables":3.675002532653351},{"nemTime":"2026-01-31T19:45:00+10:00","hour":19,"minute":45,"importKwh":0.093,"exportKwh":0,"importPrice":37.42248,"exportPrice":11.55403,"importCost":3.4803,"exportRevenue":0,"descriptor":"low","spikeStatus":"none","period":"peak","renewables":4.213454921101996},{"nemTime":"2026-01-31T19:50:00+10:00","hour":19,"minute":50,"importKwh":0.091,"exportKwh":0,"importPrice":38.74722,"exportPrice":12.75835,"importCost":3.526,"exportRevenue":0,"descriptor":"low","spikeStatus":"none","period":"peak","renewables":4.56992994731235},{"nemTime":"2026-01-31T19:55:00+10:00","hour":19,"minute":55,"importKwh":0.087,"exportKwh":0,"importPrice":39.0291,"exportPrice":13.0146,"importCost":3.3955,"exportRevenue":0,"descriptor":"low","spikeStatus":"none","period":"peak","renewables":4.780652821137134},{"nemTime":"2026-01-31T20:00:00+10:00","hour":20,"minute":0,"importKwh":0.097,"exportKwh":0,"importPrice":38.74722,"exportPrice":12.75835,"importCost":3.7585,"exportRevenue":0,"descriptor":"low","spikeStatus":"none","period":"peak","renewables":5.293909420907741},{"nemTime":"2026-01-31T20:05:00+10:00","hour":20,"minute":5,"importKwh":0.105,"exportKwh":0,"importPrice":36.91444,"exportPrice":11.09218,"importCost":3.876,"exportRevenue":0,"descriptor":"low","spikeStatus":"none","period":"peak","renewables":5.785952558311347},{"nemTime":"2026-01-31T20:10:00+10:00","hour":20,"minute":10,"importKwh":0.1,"exportKwh":0,"importPrice":36.67019,"exportPrice":10.87014,"importCost":3.667,"exportRevenue":0,"descriptor":"low","spikeStatus":"none","period":"peak","renewables":6.033156480186252},{"nemTime":"2026-01-31T20:15:00+10:00","hour":20,"minute":15,"importKwh":0.099,"exportKwh":0,"importPrice":36.65841,"exportPrice":10.85943,"importCost":3.6292,"exportRevenue":0,"descriptor":"low","spikeStatus":"none","period":"peak","renewables":6.497698679859047},{"nemTime":"2026-01-31T20:20:00+10:00","hour":20,"minute":20,"importKwh":0.096,"exportKwh":0,"importPrice":36.65336,"exportPrice":10.85484,"importCost":3.5187,"exportRevenue":0,"descriptor":"low","spikeStatus":"none","period":"peak","renewables":6.587509535011823},{"nemTime":"2026-01-31T20:25:00+10:00","hour":20,"minute":25,"importKwh":0.092,"exportKwh":0,"importPrice":36.91444,"exportPrice":11.09218,"importCost":3.3961,"exportRevenue":0,"descriptor":"low","spikeStatus":"none","period":"peak","renewables":6.904580792068152},{"nemTime":"2026-01-31T20:30:00+10:00","hour":20,"minute":30,"importKwh":0.091,"exportKwh":0,"importPrice":36.91444,"exportPrice":11.09218,"importCost":3.3592,"exportRevenue":0,"descriptor":"low","spikeStatus":"none","period":"peak","renewables":6.925332029719413},{"nemTime":"2026-01-31T20:35:00+10:00","hour":20,"minute":35,"importKwh":0.124,"exportKwh":0,"importPrice":36.87701,"exportPrice":11.05816,"importCost":4.5727,"exportRevenue":0,"descriptor":"low","spikeStatus":"none","period":"peak","renewables":7.0379232646150784},{"nemTime":"2026-01-31T20:40:00+10:00","hour":20,"minute":40,"importKwh":0.132,"exportKwh":0,"importPrice":36.91444,"exportPrice":11.09218,"importCost":4.8727,"exportRevenue":0,"descriptor":"low","spikeStatus":"none","period":"peak","renewables":6.921087216762982},{"nemTime":"2026-01-31T20:45:00+10:00","hour":20,"minute":45,"importKwh":0.145,"exportKwh":0,"importPrice":38.74488,"exportPrice":12.75622,"importCost":5.618,"exportRevenue":0,"descriptor":"low","spikeStatus":"none","period":"peak","renewables":7.052271156732952},{"nemTime":"2026-01-31T20:50:00+10:00","hour":20,"minute":50,"importKwh":0.174,"exportKwh":0,"importPrice":36.87701,"exportPrice":11.05816,"importCost":6.4166,"exportRevenue":0,"descriptor":"low","spikeStatus":"none","period":"peak","renewables":7.342186121683174},{"nemTime":"2026-01-31T20:55:00+10:00","hour":20,"minute":55,"importKwh":0.149,"exportKwh":0,"importPrice":36.14367,"exportPrice":10.39148,"importCost":5.3854,"exportRevenue":0,"descriptor":"low","spikeStatus":"none","period":"peak","renewables":7.76686352425322},{"nemTime":"2026-01-31T21:00:00+10:00","hour":21,"minute":0,"importKwh":0.14,"exportKwh":0,"importPrice":35.35067,"exportPrice":9.67057,"importCost":4.9491,"exportRevenue":0,"descriptor":"low","spikeStatus":"none","period":"peak","renewables":8.176773264492562},{"nemTime":"2026-01-31T21:05:00+10:00","hour":21,"minute":5,"importKwh":0.156,"exportKwh":0,"importPrice":20.96554,"exportPrice":11.09218,"importCost":3.2706,"exportRevenue":0,"descriptor":"veryLow","spikeStatus":"none","period":"shoulder","renewables":8.602247801843092},{"nemTime":"2026-01-31T21:10:00+10:00","hour":21,"minute":10,"importKwh":0.319,"exportKwh":0,"importPrice":20.96554,"exportPrice":11.09218,"importCost":6.688,"exportRevenue":0,"descriptor":"veryLow","spikeStatus":"none","period":"shoulder","renewables":8.667654639991387},{"nemTime":"2026-01-31T21:15:00+10:00","hour":21,"minute":15,"importKwh":0.619,"exportKwh":0,"importPrice":22.76791,"exportPrice":12.7307,"importCost":14.0933,"exportRevenue":0,"descriptor":"veryLow","spikeStatus":"none","period":"shoulder","renewables":8.640465464522338},{"nemTime":"2026-01-31T21:20:00+10:00","hour":21,"minute":20,"importKwh":0.605,"exportKwh":0,"importPrice":19.02381,"exportPrice":9.32698,"importCost":11.5094,"exportRevenue":0,"descriptor":"veryLow","spikeStatus":"none","period":"shoulder","renewables":8.710480608905083},{"nemTime":"2026-01-31T21:25:00+10:00","hour":21,"minute":25,"importKwh":0.625,"exportKwh":0,"importPrice":18.19824,"exportPrice":8.57645,"importCost":11.3739,"exportRevenue":0,"descriptor":"veryLow","spikeStatus":"none","period":"shoulder","renewables":8.648695757963823},{"nemTime":"2026-01-31T21:30:00+10:00","hour":21,"minute":30,"importKwh":0.658,"exportKwh":0,"importPrice":18.19824,"exportPrice":8.57645,"importCost":11.9744,"exportRevenue":0,"descriptor":"veryLow","spikeStatus":"none","period":"shoulder","renewables":8.723319882403393},{"nemTime":"2026-01-31T21:35:00+10:00","hour":21,"minute":35,"importKwh":0.645,"exportKwh":0,"importPrice":19.40177,"exportPrice":9.67057,"importCost":12.5141,"exportRevenue":0,"descriptor":"veryLow","spikeStatus":"none","period":"shoulder","renewables":8.881652208918785},{"nemTime":"2026-01-31T21:40:00+10:00","hour":21,"minute":40,"importKwh":0.602,"exportKwh":0,"importPrice":19.40177,"exportPrice":9.67057,"importCost":11.6799,"exportRevenue":0,"descriptor":"veryLow","spikeStatus":"none","period":"shoulder","renewables":9.183583068365046},{"nemTime":"2026-01-31T21:45:00+10:00","hour":21,"minute":45,"importKwh":0.598,"exportKwh":0,"importPrice":17.47776,"exportPrice":7.92147,"importCost":10.4517,"exportRevenue":0,"descriptor":"veryLow","spikeStatus":"none","period":"shoulder","renewables":9.7517187658753},{"nemTime":"2026-01-31T21:50:00+10:00","hour":21,"minute":50,"importKwh":0.567,"exportKwh":0,"importPrice":17.47776,"exportPrice":7.92147,"importCost":9.9099,"exportRevenue":0,"descriptor":"veryLow","spikeStatus":"none","period":"shoulder","renewables":10.232540153126163},{"nemTime":"2026-01-31T21:55:00+10:00","hour":21,"minute":55,"importKwh":0.485,"exportKwh":0,"importPrice":16.20054,"exportPrice":6.76036,"importCost":7.8573,"exportRevenue":0,"descriptor":"veryLow","spikeStatus":"none","period":"shoulder","renewables":10.74017564684515},{"nemTime":"2026-01-31T22:00:00+10:00","hour":22,"minute":0,"importKwh":0.456,"exportKwh":0,"importPrice":16.20054,"exportPrice":6.76036,"importCost":7.3874,"exportRevenue":0,"descriptor":"veryLow","spikeStatus":"none","period":"shoulder","renewables":11.248146499414405},{"nemTime":"2026-01-31T22:05:00+10:00","hour":22,"minute":5,"importKwh":0.468,"exportKwh":0,"importPrice":15.65963,"exportPrice":6.26863,"importCost":7.3287,"exportRevenue":0,"descriptor":"veryLow","spikeStatus":"none","period":"shoulder","renewables":11.702994990575672},{"nemTime":"2026-01-31T22:10:00+10:00","hour":22,"minute":10,"importKwh":0.27,"exportKwh":0,"importPrice":16.19586,"exportPrice":6.75611,"importCost":4.3729,"exportRevenue":0,"descriptor":"veryLow","spikeStatus":"none","period":"shoulder","renewables":12.161642295168718},{"nemTime":"2026-01-31T22:15:00+10:00","hour":22,"minute":15,"importKwh":0.14,"exportKwh":0,"importPrice":16.8927,"exportPrice":7.3896,"importCost":2.365,"exportRevenue":0,"descriptor":"veryLow","spikeStatus":"none","period":"shoulder","renewables":12.435850687025802},{"nemTime":"2026-01-31T22:20:00+10:00","hour":22,"minute":20,"importKwh":0.139,"exportKwh":0,"importPrice":16.73354,"exportPrice":7.24491,"importCost":2.326,"exportRevenue":0,"descriptor":"veryLow","spikeStatus":"none","period":"shoulder","renewables":12.821312211285768},{"nemTime":"2026-01-31T22:25:00+10:00","hour":22,"minute":25,"importKwh":0.138,"exportKwh":0,"importPrice":16.34676,"exportPrice":6.89329,"importCost":2.2559,"exportRevenue":0,"descriptor":"veryLow","spikeStatus":"none","period":"shoulder","renewables":13.363934394771757},{"nemTime":"2026-01-31T22:30:00+10:00","hour":22,"minute":30,"importKwh":0.145,"exportKwh":0,"importPrice":16.34676,"exportPrice":6.89329,"importCost":2.3703,"exportRevenue":0,"descriptor":"veryLow","spikeStatus":"none","period":"shoulder","renewables":13.022776604787628},{"nemTime":"2026-01-31T22:35:00+10:00","hour":22,"minute":35,"importKwh":0.153,"exportKwh":0,"importPrice":16.33504,"exportPrice":6.88264,"importCost":2.4993,"exportRevenue":0,"descriptor":"veryLow","spikeStatus":"none","period":"shoulder","renewables":13.50382099914474},{"nemTime":"2026-01-31T22:40:00+10:00","hour":22,"minute":40,"importKwh":0.155,"exportKwh":0,"importPrice":17.27307,"exportPrice":7.73539,"importCost":2.6773,"exportRevenue":0,"descriptor":"veryLow","spikeStatus":"none","period":"shoulder","renewables":13.354247345235077},{"nemTime":"2026-01-31T22:45:00+10:00","hour":22,"minute":45,"importKwh":0.159,"exportKwh":0,"importPrice":16.34676,"exportPrice":6.89329,"importCost":2.5991,"exportRevenue":0,"descriptor":"veryLow","spikeStatus":"none","period":"shoulder","renewables":13.559192801016954},{"nemTime":"2026-01-31T22:50:00+10:00","hour":22,"minute":50,"importKwh":0.177,"exportKwh":0,"importPrice":16.70295,"exportPrice":7.2171,"importCost":2.9564,"exportRevenue":0,"descriptor":"veryLow","spikeStatus":"none","period":"shoulder","renewables":13.515961647404193},{"nemTime":"2026-01-31T22:55:00+10:00","hour":22,"minute":55,"importKwh":0.14,"exportKwh":0,"importPrice":16.33504,"exportPrice":6.88264,"importCost":2.2869,"exportRevenue":0,"descriptor":"veryLow","spikeStatus":"none","period":"shoulder","renewables":13.196761389661349},{"nemTime":"2026-01-31T23:00:00+10:00","hour":23,"minute":0,"importKwh":0.316,"exportKwh":0,"importPrice":16.33504,"exportPrice":6.88264,"importCost":5.1619,"exportRevenue":0,"descriptor":"veryLow","spikeStatus":"none","period":"shoulder","renewables":13.359672137277773},{"nemTime":"2026-01-31T23:05:00+10:00","hour":23,"minute":5,"importKwh":0.574,"exportKwh":0,"importPrice":16.34676,"exportPrice":6.89329,"importCost":9.383,"exportRevenue":0,"descriptor":"veryLow","spikeStatus":"none","period":"shoulder","renewables":13.49040260038971},{"nemTime":"2026-01-31T23:10:00+10:00","hour":23,"minute":10,"importKwh":0.521,"exportKwh":0,"importPrice":17.06872,"exportPrice":7.54962,"importCost":8.8928,"exportRevenue":0,"descriptor":"veryLow","spikeStatus":"none","period":"shoulder","renewables":13.253159156328328},{"nemTime":"2026-01-31T23:15:00+10:00","hour":23,"minute":15,"importKwh":0.534,"exportKwh":0,"importPrice":16.47232,"exportPrice":7.00744,"importCost":8.7962,"exportRevenue":0,"descriptor":"veryLow","spikeStatus":"none","period":"shoulder","renewables":13.285939835952968},{"nemTime":"2026-01-31T23:20:00+10:00","hour":23,"minute":20,"importKwh":0.496,"exportKwh":0,"importPrice":16.34323,"exportPrice":6.89008,"importCost":8.1062,"exportRevenue":0,"descriptor":"veryLow","spikeStatus":"none","period":"shoulder","renewables":13.107772054376957},{"nemTime":"2026-01-31T23:25:00+10:00","hour":23,"minute":25,"importKwh":0.486,"exportKwh":0,"importPrice":16.34676,"exportPrice":6.89329,"importCost":7.9445,"exportRevenue":0,"descriptor":"veryLow","spikeStatus":"none","period":"shoulder","renewables":13.462797870573024},{"nemTime":"2026-01-31T23:30:00+10:00","hour":23,"minute":30,"importKwh":0.479,"exportKwh":0,"importPrice":15.53066,"exportPrice":6.15138,"importCost":7.4392,"exportRevenue":0,"descriptor":"veryLow","spikeStatus":"none","period":"shoulder","renewables":14.147125672391828},{"nemTime":"2026-01-31T23:35:00+10:00","hour":23,"minute":35,"importKwh":0.453,"exportKwh":0,"importPrice":16.34676,"exportPrice":6.89329,"importCost":7.4051,"exportRevenue":0,"descriptor":"veryLow","spikeStatus":"none","period":"shoulder","renewables":14.4831517761287},{"nemTime":"2026-01-31T23:40:00+10:00","hour":23,"minute":40,"importKwh":0.453,"exportKwh":0,"importPrice":15.53066,"exportPrice":6.15138,"importCost":7.0354,"exportRevenue":0,"descriptor":"veryLow","spikeStatus":"none","period":"shoulder","renewables":14.726383252666562},{"nemTime":"2026-01-31T23:45:00+10:00","hour":23,"minute":45,"importKwh":0.448,"exportKwh":0,"importPrice":15.55543,"exportPrice":6.1739,"importCost":6.9688,"exportRevenue":0,"descriptor":"veryLow","spikeStatus":"none","period":"shoulder","renewables":14.845700999890898},{"nemTime":"2026-01-31T23:50:00+10:00","hour":23,"minute":50,"importKwh":0.415,"exportKwh":0,"importPrice":15.46737,"exportPrice":6.09385,"importCost":6.419,"exportRevenue":0,"descriptor":"veryLow","spikeStatus":"none","period":"shoulder","renewables":14.94632694910146},{"nemTime":"2026-01-31T23:55:00+10:00","hour":23,"minute":55,"importKwh":0.414,"exportKwh":0,"importPrice":15.50558,"exportPrice":6.12858,"importCost":6.4193,"exportRevenue":0,"descriptor":"veryLow","spikeStatus":"none","period":"shoulder","renewables":15.399739782755775},{"nemTime":"2026-02-01T00:00:00+10:00","hour":0,"minute":0,"importKwh":0.389,"exportKwh":0,"importPrice":15.37472,"exportPrice":6.00962,"importCost":5.9808,"exportRevenue":0,"descriptor":"veryLow","spikeStatus":"none","period":"shoulder","renewables":15.439281630396074}]}